Workbook

Sheet Totals
A1: TOTALS — BERRIDGE ZEE-LOCK (DOUBLE-LOCK)
A2: Labor and Materials pull LIVE from their tabs. Material markup is the only lever here.
A4: Material markup % | B4: 0.2
A6: Labor (from Labor tab) | B6: =Labor!E8
A7: Materials (from Material Order tab) | B7: ='Material Order'!E38
A8: Material markup (20%) | B8: =B7*B4
A9: TOTAL BID — clip boxes | B9: =B6+B7+B8
A10: TOTAL BID — continuous clip | B10: =B9+(('Bid (All-In Priced)'!I8*0.59)-'Bid (All-In Priced)'!G59)*1.0825*1.2
A11: Labor carries no markup (the ×2 in $500/man-day is its profit). Markup applies to materials only.
A12: ="Same bid both ways: clip boxes "&TEXT('Bid (All-In Priced)'!G59,"$#,##0.00")&" vs continuous "&TEXT('Bid (All-In Priced)'!I8*0.59,"$#,##0.00")&" material — difference "&TEXT(B10-B9,"$#,##0.00")&" on the total."

Sheet Bid
A1: SMS ROOFING — BERRIDGE ZEE-LOCK (DOUBLE-LOCK) • TEMPLATE — type the job into the blue cells
A2: Blue rows explain the line above with LIVE numbers. RED = raw/unrounded. Material pricing lives on the Material Order tab.
A4: 1 · PANEL TAKEOFF — quantity × length = linear feet (LF)
A5: ="A takeoff is counting what you install. Qty × Length = the LF that run needs. Sum all = total panel LF."
A6: Run | B6: Qty | C6: Length ft | I6: LF (Qty×Len)
A7: Panel LF (lump from takeoff) | B7: 1 | C7: 0 | I7: =B7*C7
A8: TOTAL PANEL LF | B8: =SUM(B7:B7) | I8: =SUM(I7:I7)
A9: ="All runs = "&B8&" panels = "&TEXT(I8,"#,##0.00")&" LF — drives coil, fab, labor, clips, vinyl. Add rows above as runs come in."
A11: 2 · PANEL SQUARES — LF into area (a ‘square’ = 100 sq ft)
A12: Panel coverage width (in) | F12: 16
A13: Panel SF = LF × (width ÷ 12) | F13: =I8*(F12/12)
A14: Panel SQUARES = SF ÷ 100 | F14: =F13/100
A15: ="Fab, labor, rivets price per square. "&TEXT(I8,"#,##0")&" LF × "&F12&"″÷12 = "&TEXT(F13,"#,##0")&" sf ÷100 = "&TEXT(F14,"0.00")&" sq."
A17: 3 · COIL — raw metal, full 1000′ (or 500′) rolls
A18: Item | B18: Need LF | C18: Coil LF | D18: Raw | E18: Coils
A19: Zee-Lock coil | B19: =I8 | C19: 500 | D19: =B19/C19 | E19: =ROUNDUP(D19,0)
A20: ="Need "&TEXT(I8,"#,##0")&" LF ÷ "&C19&"′/coil = "&TEXT(D19,"0.00")&" → buy "&E19&" × 500′ coils. (Pricing on Material Order tab.)"
A22: 4 · FLAT METAL — drip, hip/ridge, Z flash from 48″×10′ sheets
A23: ="Cut from 48″×10′ sheets. 48 ÷ stretch-out = strips across; ×10′ = LF/sheet. LF ÷ that = sheets (round UP)."
A24: Piece | B24: LF | C24: Stretch-out in | D24: LF/sheet | E24: Raw sheets | F24: Sheets
A25: D-style drip edge | B25: 0 | C25: 9.5 | D25: =FLOOR(48/C25,1)*10 | E25: =B25/D25 | F25: =ROUNDUP(E25,0)
A26: ="Drip: "&TEXT(B25,"#,##0")&" LF ÷ "&D25&" LF/sheet (48÷"&TEXT(C25,"0.0")&"″ = "&FLOOR(48/C25,1)&" strips ×10′) = "&TEXT(E25,"0.00")&" → "&F25&" sheets. (Sheet material + fab priced on other tabs.)"
A27: Drip edge cleat (only if face > 4″)
A28: Drip edge cleat: PENDING Adam — only when the drip face is over 4″. LF + stretch-out to confirm; out of every total until then.
A29: Rake-edge cap (req. Z) | B29: 0 | C29: 12 | D29: =FLOOR(48/C29,1)*10 | E29: =B29/D29 | F29: =ROUNDUP(E29,0)
A30: ="Rake-edge cap: "&TEXT(B29,"#,##0")&" LF ÷ "&D29&" LF/sheet (48÷"&TEXT(C29,"0.0")&"″ = "&FLOOR(48/C29,1)&" strips ×10′) = "&TEXT(E29,"0.00")&" → "&F29&" sheets. (Sheet material + fab priced on other tabs.)"
A31: Rake edge cleat (galv) | B31: =B29 | C31: 5 | D31: =FLOOR(48/C31,1)*10 | E31: =B31/D31 | F31: =ROUNDUP(E31,0)
A32: ="Rake edge cleat (follows rake-edge): "&TEXT(B31,"#,##0")&" LF ÷ "&D31&" LF/sheet (48÷"&TEXT(C31,"0.0")&"″ = "&FLOOR(48/C31,1)&" strips ×10′) = "&TEXT(E31,"0.00")&" → "&F31&" sheets. (Sheet material + fab priced on other tabs.)"
A33: (W) Valley | B33: 0 | C33: 24 | D33: =FLOOR(48/C33,1)*10 | E33: =B33/D33 | F33: =ROUNDUP(E33,0)
A34: ="(W) Valley: "&TEXT(B33,"#,##0")&" LF ÷ "&D33&" LF/sheet (48÷"&TEXT(C33,"0.0")&"″ = "&FLOOR(48/C33,1)&" strips ×10′) = "&TEXT(E33,"0.00")&" → "&F33&" sheets. (Sheet material + fab priced on other tabs.)"
A35: (W) Valley cleat (both sides ×2) | B35: =B33*2 | C35: 3 | D35: =FLOOR(48/C35,1)*10 | E35: =B35/D35 | F35: =ROUNDUP(E35,0)
A36: ="(W) Valley cleat (valley ×2 sides): "&TEXT(B35,"#,##0")&" LF ÷ "&D35&" LF/sheet (48÷"&TEXT(C35,"0.0")&"″ = "&FLOOR(48/C35,1)&" strips ×10′) = "&TEXT(E35,"0.00")&" → "&F35&" sheets. (Sheet material + fab priced on other tabs.)"
A37: Hip/Ridge cap (req. Z ×2 sides) | B37: 0 | C37: 16 | D37: =FLOOR(48/C37,1)*10 | E37: =B37/D37 | F37: =ROUNDUP(E37,0)
A38: ="Hip/Ridge: "&TEXT(B37,"#,##0")&" LF ÷ "&D37&" LF/sheet (48÷"&TEXT(C37,"0.0")&"″ = "&FLOOR(48/C37,1)&" strips ×10′) = "&TEXT(E37,"0.00")&" → "&F37&" sheets. (Sheet material + fab priced on other tabs.)"
A39: Rake wall (req. Z + counterflashing) | B39: 0 | C39: 12 | D39: =FLOOR(48/C39,1)*10 | E39: =B39/D39 | F39: =ROUNDUP(E39,0)
A40: ="Rake wall: "&TEXT(B39,"#,##0")&" LF ÷ "&D39&" LF/sheet (48÷"&TEXT(C39,"0.0")&"″ = "&FLOOR(48/C39,1)&" strips ×10′) = "&TEXT(E39,"0.00")&" → "&F39&" sheets. (Sheet material + fab priced on other tabs.)"
A41: Head wall (req. Z + counterflashing)
A42: Head wall: none on TEMPLATE — sample/checklist row (works like rake wall: Z + counterflash). Fill LF + SO when a job has one.
A43: Curb — L flash (req. term-bar CF) | B43: 0 | C43: 16 | D43: =FLOOR(48/C43,1)*10 | E43: =B43/D43 | F43: =ROUNDUP(E43,0)
A44: ="Curb L flash: "&TEXT(B43,"#,##0")&" LF ÷ "&D43&" LF/sheet (48÷"&TEXT(C43,"0.0")&"″ = "&FLOOR(48/C43,1)&" strips ×10′) = "&TEXT(E43,"0.00")&" → "&F43&" sheets. (Sheet material + fab priced on other tabs.)"
A45: Z flashing (BOUGHT — die-formed Zee-Closure) | B45: =B29+B37*2+B39+B41 | C45: 5 | D45: =FLOOR(48/C45,1)*10 | E45: =B45/D45 | F45: =ROUNDUP(E45,0)
A46: Z flash: rake-edge 80′ ×1 + H/R 300′ ×2 = 600′ + rake wall 30′ ×1 + head wall — = 710′. • BOUGHT: 710′ ÷ 16″ closures = 533 pcs × $1.99 = $1,060.67 (this is what the bid uses — making Zee closures by hand sucks). • BY HAND alternate: 5″ SO → the sheet count on this row (8 sheets ≈ $640 material + $320 fab).
A47: Counterflash | B47: =B39+B41 | C47: 6 | D47: =FLOOR(48/C47,1)*10 | E47: =B47/D47 | F47: =ROUNDUP(E47,0)
A48: Counterflash: rake wall 30′ + head wall — • = 30′ ÷ 80 LF/sheet = 0.38 → 1 sheet.
A49: Counterflash (term bar) | B49: =B43 | C49: 6 | D49: =FLOOR(48/C49,1)*10 | E49: =B49/D49 | F49: =ROUNDUP(E49,0)
A50: Counterflash (term bar): curb 20′ — like a term bar; fastens w/ WASHER-HEAD screws @6″ OC • = 20′ ÷ 80 LF/sheet = 0.25 → 1 sheet.
A52: 5 · ACCESSORIES
A53: Item | B53: Driver | C53: Raw | D53: Qty | E53: Pkg
A54: Caulk (under Z + drip, +1 tube/sq cover) | B54: (Z + drip LF) ÷ 20 + 1/panel sq | C54: =(B45+B25)/20+F14 | D54: =ROUNDUP((B45+B25)/20+F14,0) | E54: tube
A55: ="Caulk: (Z "&TEXT(B45,"#,##0")&" + drip "&TEXT(B25,"#,##0")&")÷20 = "&TEXT((B45+B25)/20,"0.00")&" + 1/sq cover × "&TEXT(F14,"0.00")&" sq = "&TEXT(C54,"0.00")&" → "&D54&" tubes. (Pricing on Material Order tab.)"
A56: Rivets (1 box / 10 PANEL sq) | B56: panel sq ÷ 10 | C56: =F14/10 | D56: =ROUNDUP(F14/10,0) | E56: box
A57: ="Rivets: "&TEXT(F14,"0.00")&" panel sq ÷10 (metal, not I&W)"&" → "&D56&" box. (Pricing on Material Order tab.)"
A58: Zee-Lock clips 2-1/6″ (panel LF ÷ OC) | B58: clips ÷ 300/box | C58: =ROUNDUP(I8/2,0)/300 | D58: =ROUNDUP(ROUNDUP(I8/2,0)/300,0) | E58: bx/300
A59: ="Clips: "&TEXT(I8,"#,##0")&" LF ÷ 2′ OC = "&ROUNDUP(I8/2,0)&" clips ÷300/box → "&D58&" boxes. ALTERNATE: continuous Zee-Rib "&TEXT(I8,"#,##0")&"′ × $0.59 = "&TEXT(I8*0.59,"$#,##0.00")&" — Adam picks which rides. (Pricing on Material Order tab.)"
A60: Vinyl weatherstrip — NONE on double-lock | B60: panel LF ÷ 1400 | C60: 0 | D60: 0 | E60: roll
A61: Vinyl: the double-lock seam takes NO vinyl bead (Berridge SP-21 datasheet — single-lock only). Row kept as the checklist. CONFIRM w/ Adam.
A62: Screws (per-piece OC) | B62: clips×2 +drip×2 +cleats×2 +walls×1 +curb×2 | C62: =((ROUNDUP(I8/2,0)*2)+(B25*2)+(B31*2)+(B35*2)+(B39*1)+(B41*1)+(B43*2))/250 | D62: =ROUNDUP(((ROUNDUP(I8/2,0)*2)+(B25*2)+(B31*2)+(B35*2)+(B39*1)+(B41*1)+(B43*2))/250,0) | E62: bag
A63: ="Screws: clips "&ROUNDUP(I8/2,0)&"×2 + drip "&B25&"×2 (6″OC) + rake edge cleat "&B31&"×2 (6″OC) + valley cleat "&B35&"×2 (6″OC) + rake wall "&B39&"×1 (1′OC) + head wall —×1 + curb L "&B43&"×2 (6″OC) = "&((ROUNDUP(I8/2,0)*2)+(B25*2)+(B31*2)+(B35*2)+(B39*1)+(B41*1)+(B43*2))&" ÷250/bag → "&D62&" bags. NO fastener: rake-edge cap, H/R, valley, Z, reg. counterflash."
A64: Washer-head screws (term bar CF) | B64: CF (term bar) ×2 @6″ OC | C64: =(B49*2)/250 | D64: =ROUNDUP((B49*2)/250,0) | E64: bag
A65: ="Washer-head screws: counterflash (term bar) "&B49&"′ ×2 (6″ OC) = "&(B49*2)&" ÷250/bag → "&D64&" bag. Different fastener — washer head, not the regular screw."
A67: 6 · HIGH-TEMP ICE & WATER SHIELD
A68: Field area (sf) | F68: 0 | G68: Pitch | H68: Factor
A69: Pitch (rise / 12) — ASKED per job | F69: 6 | G69: 1 | H69: 1.0035
A70: Pitch factor (from table →) | F70: =INDEX($H$69:$H$80,MATCH(F69,$G$69:$G$80,0)) | G70: 2 | H70: 1.0138
A71: Waste factor (×) | F71: 1.15 | G71: 3 | H71: 1.0308
A72: Material qty (sf) = field × pitch × waste | F72: =F68*F70*F71 | G72: 4 | H72: 1.0541
A73: Coverage (sq/roll) | F73: 1.8 | G73: 5 | H73: 1.0833
A74: Rolls = (qty sf ÷ 100) ÷ 1.8 | C74: =(F72/100)/F73 | D74: =ROUNDUP(C74,0) | E74: roll | G74: 6 | H74: 1.118
A75: Labor sq = field × pitch ÷ 100 (installed area) | C75: =F68*F70/100 | D75: =ROUNDUP(C75,0) | E75: sq | G75: 7 | H75: 1.1577
A76: Plastic cap nails (1 box / 40 sq; <1.25 rounds DOWN, min 1) | C76: =(F72/100)/40 | D76: =IF(C76<1.25,MAX(1,ROUNDDOWN(C76,0)),ROUNDUP(C76,0)) | E76: box | G76: 8 | H76: 1.2019
A77: ="I&W: "&TEXT(F68,"#,##0")&" sf × pitch "&F69&"/12 ("&TEXT(F70,"0.0000")&") × waste "&F71&" = "&TEXT(F72,"#,##0")&" sf ÷100÷1.8 = "&TEXT((F72/100)/F73,"0.00")&" → "&D74&" rolls. Labor "&D75&" sq (installed, no waste). Caps "&TEXT(C76,"0.00")&" <1.25 → "&D76&" box (rounds down, never below 1 — tack-down only). (All pricing on other tabs.)" | G77: 9 | H77: 1.25
G78: 10 | H78: 1.3017
G79: 11 | H79: 1.3566
G80: 12 | H80: 1.4142

Sheet Material Order
A1: MATERIAL ORDER — BERRIDGE ZEE-LOCK (DOUBLE-LOCK)
A2: Quantities pull LIVE from the bid. Send the PURCHASED block to your supplier; the fab line is in-house.
A4: PURCHASED MATERIALS (send to supplier)
A5: Item | B5: Qty | C5: Unit | D5: Unit $ | E5: Line Total
A6: Zee-Lock coil (500′) | B6: ='Bid (All-In Priced)'!E19 | C6: coil | D6: =500*(20.875/12)*1.82 | E6: =B6*D6
A7: Flat sheet — D-style drip edge | B7: ='Bid (All-In Priced)'!F25 | C7: sheet | D7: =IF(N(B7)=0,"-",80) | E7: =IF(N(B7)=0,"-",B7*D7)
A8: Galv sheet — Drip edge cleat (PENDING) | B8: ='Bid (All-In Priced)'!F27 | C8: sheet | D8: =IF(N(B8)=0,"-",60) | E8: =IF(N(B8)=0,"-",B8*D8)
A9: Flat sheet — Rake-edge cap | B9: ='Bid (All-In Priced)'!F29 | C9: sheet | D9: =IF(N(B9)=0,"-",80) | E9: =IF(N(B9)=0,"-",B9*D9)
A10: Galv sheet — Rake edge cleat | B10: ='Bid (All-In Priced)'!F31 | C10: sheet | D10: =IF(N(B10)=0,"-",60) | E10: =IF(N(B10)=0,"-",B10*D10)
A11: Flat sheet — (W) Valley | B11: ='Bid (All-In Priced)'!F33 | C11: sheet | D11: =IF(N(B11)=0,"-",80) | E11: =IF(N(B11)=0,"-",B11*D11)
A12: Galv sheet — (W) Valley cleat | B12: ='Bid (All-In Priced)'!F35 | C12: sheet | D12: =IF(N(B12)=0,"-",60) | E12: =IF(N(B12)=0,"-",B12*D12)
A13: Flat sheet — Hip/Ridge cap | B13: ='Bid (All-In Priced)'!F37 | C13: sheet | D13: =IF(N(B13)=0,"-",80) | E13: =IF(N(B13)=0,"-",B13*D13)
A14: Flat sheet — Rake wall | B14: ='Bid (All-In Priced)'!F39 | C14: sheet | D14: =IF(N(B14)=0,"-",80) | E14: =IF(N(B14)=0,"-",B14*D14)
A15: Flat sheet — Head wall (sample) | B15: ='Bid (All-In Priced)'!F41 | C15: sheet | D15: =IF(N(B15)=0,"-",80) | E15: =IF(N(B15)=0,"-",B15*D15)
A16: Flat sheet — Curb L flash | B16: ='Bid (All-In Priced)'!F43 | C16: sheet | D16: =IF(N(B16)=0,"-",80) | E16: =IF(N(B16)=0,"-",B16*D16)
A17: Berridge Die-Formed Zee-Closure (710′ ÷ 16″) | B17: =ROUNDUP('Bid (All-In Priced)'!B45/(16/12),0) | C17: pc | D17: 1.99 | E17: =B17*D17
A18: Flat sheet — Counterflash | B18: ='Bid (All-In Priced)'!F47 | C18: sheet | D18: =IF(N(B18)=0,"-",80) | E18: =IF(N(B18)=0,"-",B18*D18)
A19: Flat sheet — Counterflash (term bar) | B19: ='Bid (All-In Priced)'!F49 | C19: sheet | D19: =IF(N(B19)=0,"-",80) | E19: =IF(N(B19)=0,"-",B19*D19)
A20: Caulk | B20: ='Bid (All-In Priced)'!D55 | C20: tube | D20: =IF(N(B20)=0,"-",10) | E20: =IF(N(B20)=0,"-",B20*D20)
A21: Rivets | B21: ='Bid (All-In Priced)'!D57 | C21: box | D21: =IF(N(B21)=0,"-",50) | E21: =IF(N(B21)=0,"-",B21*D21)
A22: Berridge Zee-Lock Clip 2-1/6" (300/box) | B22: ='Bid (All-In Priced)'!D59 | C22: box | D22: =IF(N(B22)=0,"-",174) | E22: =IF(N(B22)=0,"-",B22*D22)
A23: Vinyl — NONE on double-lock | B23: ='Bid (All-In Priced)'!D61 | C23: roll | D23: =IF(N(B23)=0,"-",392) | E23: =IF(N(B23)=0,"-",B23*D23)
A24: Screws (250/bag) | B24: ='Bid (All-In Priced)'!D63 | C24: bag | D24: =IF(N(B24)=0,"-",20) | E24: =IF(N(B24)=0,"-",B24*D24)
A25: Washer-head screws (250/bag) | B25: ='Bid (All-In Priced)'!D65 | C25: bag | D25: =IF(N(B25)=0,"-",20) | E25: =IF(N(B25)=0,"-",B25*D25)
A26: Hi-Temp Ice & Water | B26: ='Bid (All-In Priced)'!D76 | C26: roll | D26: =IF(N(B26)=0,"-",120) | E26: =IF(N(B26)=0,"-",B26*D26)
A27: Plastic cap nails | B27: ='Bid (All-In Priced)'!D78 | C27: box | D27: =IF(N(B27)=0,"-",25) | E27: =IF(N(B27)=0,"-",B27*D27)
A28: Delivery — standing seam (×2 trips) | B28: 2 | C28: trip | D28: 200 | E28: =B28*D28
A29: SP-21 panel machine rental (thru supply house) | B29: 2 | C29: week | D29: 1400 | E29: =B29*D29
A30: Purchased subtotal | E30: =SUM(E6:E29)
A32: IN-HOUSE (not ordered — a material-side cost in the bid)
A33: Item | B33: Qty | C33: Unit | D33: Unit $ | E33: Line Total
A34: Panel roll-form fabrication | B34: ='Bid (All-In Priced)'!F14 | C34: sq | D34: 40 | E34: =B34*D34
A36: MATERIAL SUBTOTAL (purchased + fab) | E36: =E30+E34
A37: Sales tax (8.25%) | E37: =E36*0.0825
A38: MATERIAL TOTAL (w/ tax) | E38: =E36+E37
A40: Blue = editable unit price. Qty is live from the bid. ‘Material total (w/tax)’ feeds both bid tabs.

Sheet Labor
A1: LABOR — BERRIDGE ZEE-LOCK (DOUBLE-LOCK)
A2: Qty pulls LIVE from the bid. No tax on labor (new con). The ×2 inside $500/man-day IS the labor profit.
A4: Line | B4: Qty | C4: Unit | D4: Rate | E4: Total
A5: Panel install (incl. ALL flat-metal install) | B5: ='Bid (All-In Priced)'!F14 | C5: sq | D5: =INDEX($D$14:$D$25,MATCH('Bid (All-In Priced)'!F71,$A$14:$A$25,0)) | E5: =B5*D5
A6: Ice & Water install | B6: ='Bid (All-In Priced)'!D77 | C6: sq | D6: =INDEX($C$14:$C$25,MATCH('Bid (All-In Priced)'!F71,$A$14:$A$25,0)) | E6: =B6*D6
A7: Flat-metal shop fab (all pieces) | B7: ='Bid (All-In Priced)'!F25+'Bid (All-In Priced)'!F29+'Bid (All-In Priced)'!F31+'Bid (All-In Priced)'!F33+'Bid (All-In Priced)'!F35+'Bid (All-In Priced)'!F37+'Bid (All-In Priced)'!F39+'Bid (All-In Priced)'!F43+'Bid (All-In Priced)'!F47+'Bid (All-In Priced)'!F49 | C7: sheet | D7: 40 | E7: =B7*D7
A8: LABOR TOTAL (no tax) | E8: =SUM(E5:E7)
A9: Blue = editable rate (charts below). Panel + I&W rates follow pitch automatically. 'Labor total' feeds the bid.
A10: Blue = editable rate. Qty live from bid. $250/sq covers panels AND all flat-metal field install. ‘Labor total’ feeds the bid.
A12: LABOR RATES BY PITCH ($/sq)
A13: Pitch | B13: Felt | C13: Ice & Water | D13: Panels
A14: 1 | B14: 20 | C14: 40 | D14: 270
A15: 2 | B15: 20 | C15: 40 | D15: 270
A16: 3 | B16: 20 | C16: 40 | D16: 270
A17: 4 | B17: 20 | C17: 40 | D17: 270
A18: 5 | B18: 20 | C18: 40 | D18: 270
A19: 6 | B19: 20 | C19: 40 | D19: 270
A20: 7 | B20: 22 | C20: 42 | D20: 280
A21: 8 | B21: 24 | C21: 44 | D21: 290
A22: 9 | B22: 26 | C22: 46 | D22: 300
A23: 10 | B23: 28 | C23: 48 | D23: 310
A24: 11 | B24: 30 | C24: 50 | D24: 320
A25: 12 | B25: 32 | C25: 52 | D25: 330
A26: Rates pull from the pitch typed on the bid (6/12 on TEMPLATE). PANELS start $270 on Zee-Lock — hand seam + machine for the double lock. Fab stays $40/sheet.

Sheet Bid (All-In Priced)
A1: SMS ROOFING — BERRIDGE ZEE-LOCK (DOUBLE-LOCK) • TEMPLATE — type the job into the blue cells • BID + TAKEOFF WALK-THROUGH
A2: Blue rows explain the line above with LIVE numbers. RED = raw/unrounded.
A4: 1 · PANEL TAKEOFF — quantity × length = linear feet (LF)
A5: ="A takeoff is counting what you install. Qty × Length = the LF that run needs. Sum all = total panel LF."
A6: Run | B6: Qty | C6: Length ft | I6: LF (Qty×Len)
A7: Panel LF (lump from takeoff) | B7: 1 | C7: 0 | I7: =B7*C7
A8: TOTAL PANEL LF | B8: =SUM(B7:B7) | I8: =SUM(I7:I7)
A9: ="All runs = "&B8&" panels = "&TEXT(I8,"#,##0.00")&" LF — drives coil, fab, labor, clips, vinyl. Add rows above as runs come in."
A11: 2 · PANEL SQUARES — LF into area (a ‘square’ = 100 sq ft)
A12: Panel coverage width (in) | F12: 16
A13: Panel SF = LF × (width ÷ 12) | F13: =I8*(F12/12)
A14: Panel SQUARES = SF ÷ 100 | F14: =F13/100
A15: ="Fab, labor, rivets price per square. "&TEXT(I8,"#,##0")&" LF × "&F12&"″÷12 = "&TEXT(F13,"#,##0")&" sf ÷100 = "&TEXT(F14,"0.00")&" sq."
A17: 3 · COIL — raw metal, full 1000′ (or 500′) rolls
A18: Item | B18: Need LF | C18: Coil LF | D18: Raw | E18: Coils | F18: $/coil | G18: Cost | I18: w/ tax
A19: Zee-Lock coil | B19: =I8 | C19: 500 | D19: =B19/C19 | E19: =ROUNDUP(D19,0) | F19: =C19*(20.875/12)*1.82 | G19: =E19*F19 | I19: =G19*1.0825
A20: ="Need "&TEXT(I8,"#,##0")&" LF ÷"&C19&" = "&TEXT(D19,"0.00")&" → "&E19&" coils. Price "&C19&"×(20.875÷12)×$1.82 = "&TEXT(F19,"$#,##0")&". Cost "&TEXT(G19,"$#,##0")&" +tax = "&TEXT(I19,"$#,##0.00")&"."
A22: 4 · FLAT METAL — drip, hip/ridge, Z flash from 48″×10′ sheets
A23: ="Cut from 48″×10′ sheets. 48 ÷ stretch-out = strips across; ×10′ = LF/sheet. LF ÷ that = sheets (round UP)."
A24: Piece | B24: LF | C24: Stretch-out in | D24: LF/sheet | E24: Raw sheets | F24: Sheets | G24: $/sheet | H24: Material | I24: Fab
A25: D-style drip edge | B25: 0 | C25: 9.5 | D25: =FLOOR(48/C25,1)*10 | E25: =B25/D25 | F25: =ROUNDUP(E25,0) | G25: 80 | H25: =F25*G25 | I25: =F25*40
A26: ="Drip: "&TEXT(B25,"#,##0")&" LF ÷ "&D25&" LF/sheet = "&TEXT(E25,"0.00")&" → "&F25&" sheets. Material "&F25&"×$80 = "&TEXT(H25,"$#,##0.00")&"; fab "&F25&"×$40 = "&TEXT(I25,"$#,##0.00")&"."
A27: Drip edge cleat (only if face > 4″)
A28: Drip edge cleat: PENDING Adam — only when the drip face is over 4″. LF + stretch-out to confirm; out of every total until then.
A29: Rake-edge cap (req. Z) | B29: 0 | C29: 12 | D29: =FLOOR(48/C29,1)*10 | E29: =B29/D29 | F29: =ROUNDUP(E29,0) | G29: 80 | H29: =F29*G29 | I29: =F29*40
A30: ="Rake-edge cap: "&TEXT(B29,"#,##0")&" LF ÷ "&D29&" LF/sheet = "&TEXT(E29,"0.00")&" → "&F29&" sheets. Material "&F29&"×$80 = "&TEXT(H29,"$#,##0.00")&"; fab "&F29&"×$40 = "&TEXT(I29,"$#,##0.00")&"."
A31: Rake edge cleat (galv) | B31: =B29 | C31: 5 | D31: =FLOOR(48/C31,1)*10 | E31: =B31/D31 | F31: =ROUNDUP(E31,0) | G31: 60 | H31: =F31*G31 | I31: =F31*40
A32: ="Rake edge cleat (follows rake-edge): "&TEXT(B31,"#,##0")&" LF ÷ "&D31&" LF/sheet = "&TEXT(E31,"0.00")&" → "&F31&" sheets. Material "&F31&"×$60 = "&TEXT(H31,"$#,##0.00")&"; fab "&F31&"×$40 = "&TEXT(I31,"$#,##0.00")&"."
A33: (W) Valley | B33: 0 | C33: 24 | D33: =FLOOR(48/C33,1)*10 | E33: =B33/D33 | F33: =ROUNDUP(E33,0) | G33: 80 | H33: =F33*G33 | I33: =F33*40
A34: ="(W) Valley: "&TEXT(B33,"#,##0")&" LF ÷ "&D33&" LF/sheet = "&TEXT(E33,"0.00")&" → "&F33&" sheets. Material "&F33&"×$80 = "&TEXT(H33,"$#,##0.00")&"; fab "&F33&"×$40 = "&TEXT(I33,"$#,##0.00")&"."
A35: (W) Valley cleat (both sides ×2) | B35: =B33*2 | C35: 3 | D35: =FLOOR(48/C35,1)*10 | E35: =B35/D35 | F35: =ROUNDUP(E35,0) | G35: 60 | H35: =F35*G35 | I35: =F35*40
A36: ="(W) Valley cleat (valley ×2 sides): "&TEXT(B35,"#,##0")&" LF ÷ "&D35&" LF/sheet = "&TEXT(E35,"0.00")&" → "&F35&" sheets. Material "&F35&"×$60 = "&TEXT(H35,"$#,##0.00")&"; fab "&F35&"×$40 = "&TEXT(I35,"$#,##0.00")&"."
A37: Hip/Ridge cap (req. Z ×2 sides) | B37: 0 | C37: 16 | D37: =FLOOR(48/C37,1)*10 | E37: =B37/D37 | F37: =ROUNDUP(E37,0) | G37: 80 | H37: =F37*G37 | I37: =F37*40
A38: ="Hip/Ridge: "&TEXT(B37,"#,##0")&" LF ÷ "&D37&" LF/sheet = "&TEXT(E37,"0.00")&" → "&F37&" sheets. Material "&F37&"×$80 = "&TEXT(H37,"$#,##0.00")&"; fab "&F37&"×$40 = "&TEXT(I37,"$#,##0.00")&"."
A39: Rake wall (req. Z + counterflashing) | B39: 0 | C39: 12 | D39: =FLOOR(48/C39,1)*10 | E39: =B39/D39 | F39: =ROUNDUP(E39,0) | G39: 80 | H39: =F39*G39 | I39: =F39*40
A40: ="Rake wall: "&TEXT(B39,"#,##0")&" LF ÷ "&D39&" LF/sheet = "&TEXT(E39,"0.00")&" → "&F39&" sheets. Material "&F39&"×$80 = "&TEXT(H39,"$#,##0.00")&"; fab "&F39&"×$40 = "&TEXT(I39,"$#,##0.00")&"."
A41: Head wall (req. Z + counterflashing)
A42: Head wall: none on TEMPLATE — sample/checklist row (works like rake wall: Z + counterflash). Fill LF + SO when a job has one.
A43: Curb — L flash (req. term-bar CF) | B43: 0 | C43: 16 | D43: =FLOOR(48/C43,1)*10 | E43: =B43/D43 | F43: =ROUNDUP(E43,0) | G43: 80 | H43: =F43*G43 | I43: =F43*40
A44: ="Curb L flash: "&TEXT(B43,"#,##0")&" LF ÷ "&D43&" LF/sheet = "&TEXT(E43,"0.00")&" → "&F43&" sheets. Material "&F43&"×$80 = "&TEXT(H43,"$#,##0.00")&"; fab "&F43&"×$40 = "&TEXT(I43,"$#,##0.00")&"."
A45: Z flashing (BOUGHT — die-formed Zee-Closure) | B45: =B29+B37*2+B39+B41 | C45: 5 | D45: =FLOOR(48/C45,1)*10 | E45: =B45/D45 | F45: =ROUNDUP(E45,0)
A46: Z flash: rake-edge 80′ ×1 + H/R 300′ ×2 = 600′ + rake wall 30′ ×1 + head wall — = 710′. • BOUGHT: 710′ ÷ 16″ closures = 533 pcs × $1.99 = $1,060.67 (this is what the bid uses — making Zee closures by hand sucks). • BY HAND alternate: 5″ SO → the sheet count on this row (8 sheets ≈ $640 material + $320 fab).
A47: Counterflash | B47: =B39+B41 | C47: 6 | D47: =FLOOR(48/C47,1)*10 | E47: =B47/D47 | F47: =ROUNDUP(E47,0) | G47: 80 | H47: =F47*G47 | I47: =F47*40
A48: Counterflash: rake wall 30′ + head wall — • = 30′ ÷ 80 LF/sheet = 0.38 → 1 sheet.
A49: Counterflash (term bar) | B49: =B43 | C49: 6 | D49: =FLOOR(48/C49,1)*10 | E49: =B49/D49 | F49: =ROUNDUP(E49,0) | G49: 80 | H49: =F49*G49 | I49: =F49*40
A50: Counterflash (term bar): curb 20′ — like a term bar; fastens w/ WASHER-HEAD screws @6″ OC • = 20′ ÷ 80 LF/sheet = 0.25 → 1 sheet.
A51: Subtotal flat metal fab (labor) | H51: =H25+H29+H31+H33+H35+H37+H39+H43+H47+H49 | I51: =I25+I29+I31+I33+I35+I37+I39+I43+I47+I49
A53: 5 · ACCESSORIES
A54: Item | B54: Driver | C54: Raw | D54: Qty | E54: Pkg | F54: $/pkg | G54: Cost | I54: w/ tax
A55: Caulk (under Z + drip, +1 tube/sq cover) | B55: (Z + drip LF) ÷ 20 + 1/panel sq | C55: =(B45+B25)/20+F14 | D55: =ROUNDUP((B45+B25)/20+F14,0) | E55: tube | F55: 10 | G55: =D55*F55 | I55: =G55*1.0825
A56: ="Caulk: (Z "&TEXT(B45,"#,##0")&" + drip "&TEXT(B25,"#,##0")&")÷20 = "&TEXT((B45+B25)/20,"0.00")&" + 1/sq × "&TEXT(F14,"0.00")&" = "&TEXT(C55,"0.00")&" → "&D55&" tubes ×$"&F55&" = "&TEXT(G55,"$#,##0.00")&" +tax "&TEXT(I55,"$#,##0.00")&"."
A57: Rivets (1 box / 10 PANEL sq) | B57: panel sq ÷ 10 | C57: =F14/10 | D57: =ROUNDUP(F14/10,0) | E57: box | F57: 50 | G57: =D57*F57 | I57: =G57*1.0825
A58: ="Rivets: "&TEXT(F14,"0.00")&" panel sq ÷10 (metal, not I&W)"&" → "&D57&" box ×$"&F57&" = "&TEXT(G57,"$#,##0.00")&" +tax "&TEXT(I57,"$#,##0.00")&"."
A59: Zee-Lock clips 2-1/6″ (panel LF ÷ OC) | B59: clips ÷ 300/box | C59: =ROUNDUP(I8/2,0)/300 | D59: =ROUNDUP(ROUNDUP(I8/2,0)/300,0) | E59: bx/300 | F59: 174 | G59: =D59*F59 | I59: =G59*1.0825
A60: ="Clips: "&ROUNDUP(I8/2,0)&" ÷300/box → "&D59&" bx ×$"&F59&" = "&TEXT(G59,"$#,##0.00")&". ALTERNATE continuous Zee-Rib: "&TEXT(I8,"#,##0")&"′×$0.59 = "&TEXT(I8*0.59,"$#,##0.00")&" → swings the BID "&TEXT((I8*0.59-G59)*1.0825*1.2,"+$#,##0.00;-$#,##0.00")&". Adam picks."
A61: Vinyl weatherstrip — NONE on double-lock | B61: panel LF ÷ 1400 | C61: 0 | D61: 0 | E61: roll | F61: 392 | G61: 0 | I61: 0
A62: Vinyl: the double-lock seam takes NO vinyl bead (Berridge SP-21 datasheet — single-lock only). Row kept as the checklist. CONFIRM w/ Adam.
A63: Screws (per-piece OC) | B63: clips×2 +drip×2 +cleats×2 +walls×1 +curb×2 | C63: =((ROUNDUP(I8/2,0)*2)+(B25*2)+(B31*2)+(B35*2)+(B39*1)+(B41*1)+(B43*2))/250 | D63: =ROUNDUP(((ROUNDUP(I8/2,0)*2)+(B25*2)+(B31*2)+(B35*2)+(B39*1)+(B41*1)+(B43*2))/250,0) | E63: bag | F63: 20 | G63: =D63*F63 | I63: =G63*1.0825
A64: ="Screws: clips "&ROUNDUP(I8/2,0)&"×2 + drip "&B25&"×2 + rake edge cleat "&B31&"×2 + valley cleat "&B35&"×2 + rake wall "&B39&"×1 + curb L "&B43&"×2 = "&((ROUNDUP(I8/2,0)*2)+(B25*2)+(B31*2)+(B35*2)+(B39*1)+(B41*1)+(B43*2))&" ÷250/bag → "&D63&" bags ×$"&F63&" = "&TEXT(G63,"$#,##0.00")&" +tax "&TEXT(I63,"$#,##0.00")&". No fastener: rake-edge cap, H/R, valley, Z, reg. CF."
A65: Washer-head screws (term bar CF) | B65: CF (term bar) ×2 @6″ OC | C65: =(B49*2)/250 | D65: =ROUNDUP((B49*2)/250,0) | E65: bag | F65: 20 | G65: =D65*F65 | I65: =G65*1.0825
A66: ="Washer-head screws: CF (term bar) "&B49&"′ ×2 (6″ OC) = "&(B49*2)&" ÷250/bag → "&D65&" bag ×$"&F65&" = "&TEXT(G65,"$#,##0.00")&" +tax "&TEXT(I65,"$#,##0.00")&"."
A67: Subtotal accessories | G67: =SUM(G55:G65) | I67: =I55+I57+I59+I61+I63+I65
A69: 6 · HIGH-TEMP ICE & WATER SHIELD
A70: Field area (sf) | F70: 0
A71: Pitch (rise / 12) — ASKED per job | F71: 6
A72: Pitch factor (table on Bid tab) | F72: =INDEX(Bid!$H$69:$H$80,MATCH(F71,Bid!$G$69:$G$80,0))
A73: Waste factor (×) | F73: 1.15
A74: Material qty (sf) = field × pitch × waste | F74: =F70*F72*F73
A75: Coverage (sq/roll) | F75: 1.8
A76: Rolls = (qty sf ÷ 100) ÷ 1.8 | C76: =(F74/100)/F75 | D76: =ROUNDUP(C76,0) | E76: roll | F76: 120 | G76: =D76*F76 | I76: =G76*1.0825
A77: Labor sq = field × pitch ÷ 100 → × rate by pitch | C77: =F70*F72/100 | D77: =ROUNDUP(C77,0) | E77: sq | F77: =INDEX(Labor!$C$14:$C$25,MATCH(F71,Labor!$A$14:$A$25,0)) | G77: =D77*F77
A78: Plastic cap nails (1 box / 40 sq; <1.25 rounds DOWN, min 1) | C78: =(F74/100)/40 | D78: =IF(C78<1.25,MAX(1,ROUNDDOWN(C78,0)),ROUNDUP(C78,0)) | E78: box | F78: 25 | G78: =D78*F78 | I78: =G78*1.0825
A79: ="I&W: "&TEXT(F70,"#,##0")&" × pitch "&F71&"/12 ("&TEXT(F72,"0.0000")&") × waste "&F73&" = "&TEXT(F74,"#,##0")&" sf ÷100÷1.8 = "&TEXT((F74/100)/F75,"0.00")&" → "&D76&" rolls (=$"&TEXT(G76,"#,##0")&" +tax "&TEXT(I76,"$#,##0.00")&"). Labor "&D77&" sq ×$40 = "&TEXT(G77,"$#,##0.00")&". Caps "&TEXT(C78,"0.00")&" <1.25 → "&D78&" box (min 1)."
A81: 7 · LABOR (no tax — new construction)
A82: Line | C82: Qty | D82: Rate | I82: Total
A83: Panel install (incl. ALL flat-metal install) | C83: =F14 | D83: =INDEX(Labor!$D$14:$D$25,MATCH(F71,Labor!$A$14:$A$25,0)) | I83: =C83*D83
A84: Ice & Water install | C84: =D77 | D84: =INDEX(Labor!$C$14:$C$25,MATCH(F71,Labor!$A$14:$A$25,0)) | I84: =C84*D84
A85: Flat-metal shop fab (all pieces) | C85: =(F25+F29+F31+F33+F35+F37+F39+F43+F47+F49) | D85: 40 | I85: =C85*D85
A86: LABOR SUBTOTAL | I86: =SUM(I83:I85)
A88: 8 · TOTALS
A89: Panel fabrication (roll-form) = sq × $40 | H89: =F14*40 | I89: =H89*1.0825
A90: Bucket | H90: Cost | I90: w/ tax
A91: MATERIAL (from Material Order tab, w/ tax) | I91: ='Material Order'!E38
A92: LABOR (no tax) | I92: =I86
A93: COST TOTAL (material w/tax + labor) | I93: =I91+I86
A94: ="Tax on MATERIAL only (8.25%). Material (from order tab, w/tax) "&TEXT(I91,"$#,##0.00")&" + labor "&TEXT(I86,"$#,##0.00")&" = COST "&TEXT(I93,"$#,##0.00")&"."
A96: SELL (material markup 20%)
A97: Material markup (×) | F97: 1.2
A98: Material (w/tax × markup) | I98: =I91*F97
A99: Labor (×2 baked in) | I99: =I86
A100: BID (sell) | I100: =I98+I86
A101: ="Sell = material w/tax "&TEXT(I91,"$#,##0.00")&" × "&F97&" + labor "&TEXT(I86,"$#,##0.00")&" = BID "&TEXT(I100,"$#,##0.00")&"."
