Workbook

Sheet Instructions
A1: SMS ROOFING — MECHANICALLY ATTACHED TPO • LOCKED ESTIMATING TEMPLATE
A2: Scope: mech-attached polyiso · mech-attached 60-mil TPO field · fully adhered TPO walls up-and-over · perimeter flat metal · penetrations and accessories. TEAR-OFF.
A4: THE PAGES — in the order you work them
A5: 1 · Takeoff | B5: THE DUMP. Only what you measure or count off the plans. Roof areas, counts, wall facets, coping / gravel stop / counter flashing / downspout runs, curbs. No materials. No pricing. Nothing derived.
A6: 2 · Material Order | B6: The order list. Every quantity reads live off the Material Takeoff page. Under each line, in plain words, is why that number is what it is — so somebody who has never been on a roof can read it and know what to change.
A7: 3 · Labor | B7: Crew cost per day ÷ squares per day = $ per square. Plus the unit-priced lines.
A8: 4 · Totals | B8: Material markup applied to material only. TOTAL BID and price per square.
A9: At the far right | B9: Plan Reference — the wall sections and kicker widths this job was read off. Material Takeoff — the working math behind every quantity on the order.
A11: HOW A LINE WORKS ON PAGE 2
A12: The pattern | B12: DRIVER x / ÷ FACTOR = RAW → QTY. The driver reads live off the Takeoff page. The FACTOR is the only cell you touch.
A13: Why | B13: Change one factor and every number downstream moves. Nothing is ever typed twice, and nothing is typed that could be calculated.
A14: The test | B14: Somebody who has never been on that roof fills in page 1 and the whole bid falls out.
A16: LEGEND
A17: Blue text | B17: Editable input — type here
A18: Green text | B18: Live link — pulls from another page. Never edit.
A19: Black text | B19: Locked formula
A20: Red text | B20: RAW / unrounded — what the math produced before rounding up to a whole package
A21: Yellow fill | B21: THE EQUATION GOES HERE — factor, divisor or rate, still to be set
A22: Blue narrow band | B22: Explains the section above in live numbers
A24: STATUS
A25: Where this stands | B25: Every product line is in place and every page is wired to the one before it. Nothing is priced and nothing is assumed.
A26: What is left | B26: Fill the yellow cells line by line. Each one is a rule stated once, then locked.
A27: If something is wrong | B27: If a product is missing, sits on the wrong page, or should not be on a mech-attached TPO job — say so and it moves or comes out.
A29: THE RULE ABOUT RULES
A30: Where equations come from | B30: Adam states them. They get built. Nothing is derived, assumed or back-filled from a number that looks close.
A31: Checks & balances | B31: Section K on the Takeoff page. Only checks Adam has stated go there — an invented check costs more to undo than it ever saved.
A32: Who this is for | B32: Adam, but also whoever runs it after him. It has to work for someone who does not know roofing.

Sheet Existing
A1: EXISTING CONDITIONS — 9506 BAMBOO, HOUSTON · WORTHAM BROTHERS
A2: Answer this page first. A question only shows up when it applies — a greyed cell is not being asked, leave it alone. How each layer is stuck down is what drives the TEAR-OFF LABOR and what shape the deck is in when it is exposed.
A4: A · WHAT KIND OF JOB IS THIS
A5: Item | B5: Answer | H5: What it turns on
A6: Construction type | H6: =IF($B$6="","pick one — nothing below this matters until you do",IF($B$6="New construction","NEW CONSTRUCTION — no existing roof. Everything below switches off.",IF($B$6="Recover","RECOVER — the existing roof stays. Still answer the layers: what stays under the new roof drives the fastener length.","TEAR OFF — every layer below is a layer that has to come off.")))
A8: B · THE DECK
A9: Item | B9: Answer | C9: Unit | H9: Note
A10: Decking | H10: the bottom of the stack. Everything above is measured from here up.
A11: =IF(OR(ISNUMBER(SEARCH("lightweight",$B$10)),ISNUMBER(SEARCH("lwic",$B$10))),"Lightweight concrete thickness","") | C11: =IF(OR(ISNUMBER(SEARCH("lightweight",$B$10)),ISNUMBER(SEARCH("lwic",$B$10))),"in","") | H11: =IF(OR(ISNUMBER(SEARCH("lightweight",$B$10)),ISNUMBER(SEARCH("lwic",$B$10))),"how thick the lightweight is. A screw has to pass through all of it to reach the steel.","not asked — the deck is not lightweight concrete")
A12: =IF(ISNUMBER(SEARCH("wood",$B$10)),"Wood deck material","") | C12: =IF(ISNUMBER(SEARCH("wood",$B$10)),"","") | H12: =IF(ISNUMBER(SEARCH("wood",$B$10)),"OSB, planks or plywood — it changes the fastener.","not asked — the deck is not wood")
A13: =IF(AND(ISNUMBER(SEARCH("steel",$B$10)),NOT(OR(ISNUMBER(SEARCH("lightweight",$B$10)),ISNUMBER(SEARCH("lwic",$B$10))))),"Steel deck profile","") | H13: =IF(AND(ISNUMBER(SEARCH("steel",$B$10)),NOT(OR(ISNUMBER(SEARCH("lightweight",$B$10)),ISNUMBER(SEARCH("lwic",$B$10))))),"R panel or B deck — the flute is what the screw lands in.","not asked — the deck is not steel")
A15: C · EXISTING ROOF LAYERS — from the deck up
A16: One question at a time, left to right. Roof type → how it is attached → gravel if it is a built-up → is there insulation under it → if yes, how the board is attached and how thick it is. Greyed = not asked. THREE LAYERS IS NOT CODE — three means tearing off is the only option.
A17: Layer | B17: Roof type | C17: Attachment | D17: Gravel? | E17: Insulation? (what board) | F17: Board attachment | G17: Board thickness (in) | H17: Note
A18: Layer 1 (on the deck) | H18: =IF($B$6="New construction","n/a — new construction has no existing layers",IF(B18="","start here — what is sitting on the deck",IF(C18="","→ how is it attached?",IF(AND(UPPER(B18)="BUR",D18=""),"→ gravel on it? Y or N",IF(E18="","→ what board is under it? N/A if none",IF(AND(UPPER(E18)<>"N/A",F18=""),"→ how is that board attached?",IF(AND(UPPER(E18)<>"N/A",G18=""),"→ how thick is that board?","done")))))))
A19: Layer 2 | H19: =IF($B$6="New construction","n/a — new construction has no existing layers",IF(B18="","answer Layer 1 first",IF(B19="","open — name it, or mark N/A if there is no Layer 2",IF(UPPER(B19)="N/A","no Layer 2. The stack stops at Layer 1.",IF(C19="","→ how is it attached?",IF(AND(UPPER(B19)="BUR",D19=""),"→ gravel on it? Y or N",IF(E19="","→ what board is under it? N/A if none",IF(AND(UPPER(E19)<>"N/A",F19=""),"→ how is that board attached?",IF(AND(UPPER(E19)<>"N/A",G19=""),"→ how thick is that board?","done")))))))))
A20: Layer 3 | H20: =IF($B$6="New construction","n/a — new construction has no existing layers",IF(B19="","answer Layer 2 first",IF(B20="","open — name it, or mark N/A if there is no Layer 3",IF(UPPER(B20)="N/A","no Layer 3. The stack stops at Layer 2.",IF(C20="","→ how is it attached?",IF(AND(UPPER(B20)="BUR",D20=""),"→ gravel on it? Y or N",IF(E20="","→ what board is under it? N/A if none",IF(AND(UPPER(E20)<>"N/A",F20=""),"→ how is that board attached?",IF(AND(UPPER(E20)<>"N/A",G20=""),"→ how thick is that board?","done")))))))))
A21: Layers counted | B21: =IF($B$6="New construction",0,COUNTIFS(B18:B20,"<>")-COUNTIFS(B18:B20,"N/A")) | H21: =IF($B$6="New construction","",IF(B21=0,"",IF(B21>=3,"THREE LAYERS. That is not code. Tear-off is the only option — a recover is off the table.",IF($B$6="Recover","recover: these layers stay put and the new roof goes over them","tear off: every layer above has to come off"))))
A27: What the new roof is and how it attaches is answered on the TAKEOFF tab, section A · SETUP. It is not asked twice.

Sheet Takeoff
A1: SMS ROOFING — 9506 BAMBOO, HOUSTON · WORTHAM BROTHERS · TAKEOFF
A2: PAGE ONE. The dump. Everything here comes off the plans or the takeoff app. Nothing is derived, nothing is priced.
A3: JOB: __________ · __________ · __________
A4: A · SETUP — what this roof IS. Everything below funnels off these.
A5: "This is the assembly, not a measurement. None of it comes off the takeoff — it comes off the spec and the manufacturer. Change the fastening pattern for a higher wind uplift and nothing else about the system changes: same sheet, same everything, different pattern."
A6: Item | B6: Value | C6: Unit | J6: Note
A7: System
A8: Deck type
A9: Lightweight concrete thickness | C9: in | J9: =IF(OR(ISNUMBER(SEARCH("lightweight",$B$8)),ISNUMBER(SEARCH("lwic",$B$8))),"how thick the lightweight pour is. A screw has to pass through all of it to reach the metal pan, so this sets the fastener length. 2 in is the usual pour.","not asked — this only comes up when the deck is lightweight concrete")
A10: Insulation thickness | C10: in
A11: Fall — where does it come from?
A12: Membrane thickness | C12: mil
A13: Field membrane sheet width (ft) | C13: ft | J13: VARIABLE — what sheet the FIELD gets is up to the job and the system. It has nothing to do with the wall, which is fastened every 5 ft no matter what sheet runs on it.
A14: ISO plates per board | C14: ea | J14: VARIABLE — ask the manufacturer for THIS system. Nothing prices until it is answered.
A15: Wall fastener spacing | C15: in o.c. | J15: THE WIND-UPLIFT LEVER — tighten this and only the fastener count moves
A16: Base flashing fastener spacing | C16: in o.c.
A18: B · ROOF AREA
A19: Item | B19: Value | C19: Unit | J19: Note
A20: Field squares | C20: sf | J20: the net field — membrane and cover board both follow this
A21: Perimeter base flashing | C21: LF | J21: HAND COUNT off the plan. Do not derive it.
A22: Curb flashing | C22: LF | E22: Curbs (count) | J22: total curb perimeter off the takeoff app — every curb added up. The COUNT beside it drives the corners.
A24: C · COUNTS — straight from the takeoff
A25: Item | B25: Qty | C25: Unit | J25: Note
A26: Curb flashing | B26: =IFERROR(IF(B22="","",B22),"") | C26: LF | J26: reads the curb flashing LF from section B — do not type it twice
A27: Pitch pans | C27: ea
A28: Pipe boots | C28: ea
A29: Scuppers | C29: ea
A30: Collector heads | C30: ea
A31: Roof hatches | C31: ea
A32: Walkpads | C32: LF
A33: Length of cricket wall | C33: LF
A34: Drains | C34: ea | J34: count off the takeoff app. On this roof they cannot be sumped — the deck already falls and the field is one flat layer.
A35: D · PARAPET WALLS — one row per facet, lumped by shared detail
A36: "DEVELOPED = the parapet above the deck + the cap width. That is the face the membrane has to cover." | N36: set this once and every wall uses it. Leave a wall blank to follow it; type on a wall to override just that one.
A37: Wall facet / section mark | B37: Length (ft) | C37: Parapet above deck (ft) | D37: Cap width (ft) | G37: DEVELOPED (ft) | H37: Sq Ft | I37: In perimeter? | J37: Note | K37: Wall substrate | L37: Substrate used
A38: Wall 1 | G38: =IFERROR(IF(AND(C38="",D38=""),"",N(C38)+N(D38)),"") | H38: =IFERROR(IF(OR(B38="",G38=""),0,B38*G38),"") | L38: =IFERROR(IF(B38="","",IF(K38<>"",K38,IF($M$36<>"",$M$36,""))),"")
A39: Wall 2 | G39: =IFERROR(IF(AND(C39="",D39=""),"",N(C39)+N(D39)),"") | H39: =IFERROR(IF(OR(B39="",G39=""),0,B39*G39),"") | L39: =IFERROR(IF(B39="","",IF(K39<>"",K39,IF($M$36<>"",$M$36,""))),"")
A40: Wall 3 | G40: =IFERROR(IF(AND(C40="",D40=""),"",N(C40)+N(D40)),"") | H40: =IFERROR(IF(OR(B40="",G40=""),0,B40*G40),"") | L40: =IFERROR(IF(B40="","",IF(K40<>"",K40,IF($M$36<>"",$M$36,""))),"")
A41: Wall 4 | G41: =IFERROR(IF(AND(C41="",D41=""),"",N(C41)+N(D41)),"") | H41: =IFERROR(IF(OR(B41="",G41=""),0,B41*G41),"") | L41: =IFERROR(IF(B41="","",IF(K41<>"",K41,IF($M$36<>"",$M$36,""))),"")
A42: Wall 5 | G42: =IFERROR(IF(AND(C42="",D42=""),"",N(C42)+N(D42)),"") | H42: =IFERROR(IF(OR(B42="",G42=""),0,B42*G42),"") | L42: =IFERROR(IF(B42="","",IF(K42<>"",K42,IF($M$36<>"",$M$36,""))),"")
A43: Wall 6 | G43: =IFERROR(IF(AND(C43="",D43=""),"",N(C43)+N(D43)),"") | H43: =IFERROR(IF(OR(B43="",G43=""),0,B43*G43),"") | L43: =IFERROR(IF(B43="","",IF(K43<>"",K43,IF($M$36<>"",$M$36,""))),"")
A44: Facet 7 | G44: =IFERROR(IF(AND(C44="",D44=""),"",N(C44)+N(D44)),"") | H44: =IFERROR(IF(OR(B44="",G44=""),0,B44*G44),"") | L44: =IFERROR(IF(B44="","",IF(K44<>"",K44,IF($M$36<>"",$M$36,""))),"")
A45: Facet 8 | G45: =IFERROR(IF(AND(C45="",D45=""),"",N(C45)+N(D45)),"") | H45: =IFERROR(IF(OR(B45="",G45=""),0,B45*G45),"") | L45: =IFERROR(IF(B45="","",IF(K45<>"",K45,IF($M$36<>"",$M$36,""))),"")
A46: TOTAL | B46: =IFERROR(SUMIF(G38:G45,">0",B38:B45),"") | H46: =IFERROR(SUM(H38:H45),"") | I46: =IFERROR(SUMIFS(B38:B45,I38:I45,"Y"),"") | J46: col I total = building PERIMETER only — anything marked N is excluded | L46: =IFERROR(IF(COUNTIF(L38:L45,"?*")=0,"",IF(COUNTIF(L38:L45,L38)=COUNTIF(L38:L45,"?*"),"every wall the same","MIXED — read each wall")),"")
A48: E · METALS — every termination, its cleat, and how it is supplied
A49: "48 ÷ stretch-out = strips across (round DOWN) · x 10 = ft per sheet · LF ÷ that = sheets (round UP). Leave a facet's stretch-out blank where that piece does not run. Each piece carries its own cleat and its own supply method."
A50: E1 · COPING CAP
A51: Fabricate in-house? | B51: Y | J51: DEFAULTS TO Y — SMS fabricates. Change to N only when somebody else is supplying it, and say who. Never leave it N by accident: N means you do not get paid for the fab.
A52: From my takeoff (LF) | C52: =IFERROR(IF(B52="","",B52-B62),"") | D52: =IFERROR(IF(B52="","",IF(ROUND(B52-B62,2)=0,"OK","CHECK")),"") | J52: the LF this piece shows on the takeoff app — this sheet builds its own from the facets; the two should agree
A53: Piece | B53: Length (ft) | C53: Stretch-out (in) | D53: Strips | E53: Ft / sheet | F53: RAW sheets | G53: Sheets | J53: Note
A54: =IFERROR(IF(A38="","",A38),"") | B54: =IFERROR(IF(B38="","",B38),"") | D54: =IFERROR(IF(NOT(UPPER(B51)="Y"),"",IF(C54="","",ROUNDDOWN(48/C54,0))),"") | E54: =IFERROR(IF(NOT(UPPER(B51)="Y"),"",IF(D54="","",D54*10)),"") | F54: =IFERROR(IF(NOT(UPPER(B51)="Y"),"",IF(OR(B54="",E54="",E54=0),"",B54/E54)),"") | G54: =IFERROR(IF(NOT(UPPER(B51)="Y"),"",IF(F54="","",ROUNDUP(F54,0))),"")
A55: =IFERROR(IF(A39="","",A39),"") | B55: =IFERROR(IF(B39="","",B39),"") | D55: =IFERROR(IF(NOT(UPPER(B51)="Y"),"",IF(C55="","",ROUNDDOWN(48/C55,0))),"") | E55: =IFERROR(IF(NOT(UPPER(B51)="Y"),"",IF(D55="","",D55*10)),"") | F55: =IFERROR(IF(NOT(UPPER(B51)="Y"),"",IF(OR(B55="",E55="",E55=0),"",B55/E55)),"") | G55: =IFERROR(IF(NOT(UPPER(B51)="Y"),"",IF(F55="","",ROUNDUP(F55,0))),"")
A56: =IFERROR(IF(A40="","",A40),"") | B56: =IFERROR(IF(B40="","",B40),"") | D56: =IFERROR(IF(NOT(UPPER(B51)="Y"),"",IF(C56="","",ROUNDDOWN(48/C56,0))),"") | E56: =IFERROR(IF(NOT(UPPER(B51)="Y"),"",IF(D56="","",D56*10)),"") | F56: =IFERROR(IF(NOT(UPPER(B51)="Y"),"",IF(OR(B56="",E56="",E56=0),"",B56/E56)),"") | G56: =IFERROR(IF(NOT(UPPER(B51)="Y"),"",IF(F56="","",ROUNDUP(F56,0))),"")
A57: =IFERROR(IF(A41="","",A41),"") | B57: =IFERROR(IF(B41="","",B41),"") | D57: =IFERROR(IF(NOT(UPPER(B51)="Y"),"",IF(C57="","",ROUNDDOWN(48/C57,0))),"") | E57: =IFERROR(IF(NOT(UPPER(B51)="Y"),"",IF(D57="","",D57*10)),"") | F57: =IFERROR(IF(NOT(UPPER(B51)="Y"),"",IF(OR(B57="",E57="",E57=0),"",B57/E57)),"") | G57: =IFERROR(IF(NOT(UPPER(B51)="Y"),"",IF(F57="","",ROUNDUP(F57,0))),"")
A58: =IFERROR(IF(A42="","",A42),"") | B58: =IFERROR(IF(B42="","",B42),"") | D58: =IFERROR(IF(NOT(UPPER(B51)="Y"),"",IF(C58="","",ROUNDDOWN(48/C58,0))),"") | E58: =IFERROR(IF(NOT(UPPER(B51)="Y"),"",IF(D58="","",D58*10)),"") | F58: =IFERROR(IF(NOT(UPPER(B51)="Y"),"",IF(OR(B58="",E58="",E58=0),"",B58/E58)),"") | G58: =IFERROR(IF(NOT(UPPER(B51)="Y"),"",IF(F58="","",ROUNDUP(F58,0))),"")
A59: =IFERROR(IF(A43="","",A43),"") | B59: =IFERROR(IF(B43="","",B43),"") | D59: =IFERROR(IF(NOT(UPPER(B51)="Y"),"",IF(C59="","",ROUNDDOWN(48/C59,0))),"") | E59: =IFERROR(IF(NOT(UPPER(B51)="Y"),"",IF(D59="","",D59*10)),"") | F59: =IFERROR(IF(NOT(UPPER(B51)="Y"),"",IF(OR(B59="",E59="",E59=0),"",B59/E59)),"") | G59: =IFERROR(IF(NOT(UPPER(B51)="Y"),"",IF(F59="","",ROUNDUP(F59,0))),"")
A60: =IFERROR(IF(A44="","",A44),"") | B60: =IFERROR(IF(B44="","",B44),"") | D60: =IFERROR(IF(NOT(UPPER(B51)="Y"),"",IF(C60="","",ROUNDDOWN(48/C60,0))),"") | E60: =IFERROR(IF(NOT(UPPER(B51)="Y"),"",IF(D60="","",D60*10)),"") | F60: =IFERROR(IF(NOT(UPPER(B51)="Y"),"",IF(OR(B60="",E60="",E60=0),"",B60/E60)),"") | G60: =IFERROR(IF(NOT(UPPER(B51)="Y"),"",IF(F60="","",ROUNDUP(F60,0))),"")
A61: Perimeter adjustment | D61: =IFERROR(IF(NOT(UPPER(B51)="Y"),"",IF(C61="","",ROUNDDOWN(48/C61,0))),"") | E61: =IFERROR(IF(NOT(UPPER(B51)="Y"),"",IF(D61="","",D61*10)),"") | F61: =IFERROR(IF(NOT(UPPER(B51)="Y"),"",IF(OR(B61="",E61="",E61=0),"",B61/E61)),"") | G61: =IFERROR(IF(NOT(UPPER(B51)="Y"),"",IF(F61="","",ROUNDUP(F61,0))),"") | J61: the metal perimeter from the takeoff, less what the rows above already cover
A62: TOTAL | B62: =IFERROR(IF(COUNT(C54:C61)=0,"",SUMIF(C54:C61,"<>",B54:B61)),"") | G62: =IFERROR(IF(OR(UPPER(B51)<>"Y",COUNT(G54:G61)=0),"",SUM(G54:G61)),"") | J62: LF counts only facets with a stretch-out. Everything to the right blanks out when this piece is prefab.
A64: E2 · GRAVEL STOP
A65: Fabricate in-house? | B65: Y | J65: DEFAULTS TO Y — SMS fabricates. Change to N only when somebody else is supplying it, and say who. Never leave it N by accident: N means you do not get paid for the fab.
A66: From my takeoff (LF) | C66: =IFERROR(IF(B66="","",B66-B76),"") | D66: =IFERROR(IF(B66="","",IF(ROUND(B66-B76,2)=0,"OK","CHECK")),"") | J66: the gravel stop run off the takeoff app. Cover tape, primer and brushes all measure against this.
A67: Piece | B67: Length (ft) | C67: Stretch-out (in) | D67: Strips | E67: Ft / sheet | F67: RAW sheets | G67: Sheets | J67: Note
A68: =IFERROR(IF(A38="","",A38),"") | B68: =IFERROR(IF(B38="","",B38),"") | D68: =IFERROR(IF(NOT(UPPER(B65)="Y"),"",IF(C68="","",ROUNDDOWN(48/C68,0))),"") | E68: =IFERROR(IF(NOT(UPPER(B65)="Y"),"",IF(D68="","",D68*10)),"") | F68: =IFERROR(IF(NOT(UPPER(B65)="Y"),"",IF(OR(B68="",E68="",E68=0),"",B68/E68)),"") | G68: =IFERROR(IF(NOT(UPPER(B65)="Y"),"",IF(F68="","",ROUNDUP(F68,0))),"")
A69: =IFERROR(IF(A39="","",A39),"") | B69: =IFERROR(IF(B39="","",B39),"") | D69: =IFERROR(IF(NOT(UPPER(B65)="Y"),"",IF(C69="","",ROUNDDOWN(48/C69,0))),"") | E69: =IFERROR(IF(NOT(UPPER(B65)="Y"),"",IF(D69="","",D69*10)),"") | F69: =IFERROR(IF(NOT(UPPER(B65)="Y"),"",IF(OR(B69="",E69="",E69=0),"",B69/E69)),"") | G69: =IFERROR(IF(NOT(UPPER(B65)="Y"),"",IF(F69="","",ROUNDUP(F69,0))),"")
A70: =IFERROR(IF(A40="","",A40),"") | B70: =IFERROR(IF(B40="","",B40),"") | D70: =IFERROR(IF(NOT(UPPER(B65)="Y"),"",IF(C70="","",ROUNDDOWN(48/C70,0))),"") | E70: =IFERROR(IF(NOT(UPPER(B65)="Y"),"",IF(D70="","",D70*10)),"") | F70: =IFERROR(IF(NOT(UPPER(B65)="Y"),"",IF(OR(B70="",E70="",E70=0),"",B70/E70)),"") | G70: =IFERROR(IF(NOT(UPPER(B65)="Y"),"",IF(F70="","",ROUNDUP(F70,0))),"")
A71: =IFERROR(IF(A41="","",A41),"") | B71: =IFERROR(IF(B41="","",B41),"") | D71: =IFERROR(IF(NOT(UPPER(B65)="Y"),"",IF(C71="","",ROUNDDOWN(48/C71,0))),"") | E71: =IFERROR(IF(NOT(UPPER(B65)="Y"),"",IF(D71="","",D71*10)),"") | F71: =IFERROR(IF(NOT(UPPER(B65)="Y"),"",IF(OR(B71="",E71="",E71=0),"",B71/E71)),"") | G71: =IFERROR(IF(NOT(UPPER(B65)="Y"),"",IF(F71="","",ROUNDUP(F71,0))),"")
A72: =IFERROR(IF(A42="","",A42),"") | B72: =IFERROR(IF(B42="","",B42),"") | D72: =IFERROR(IF(NOT(UPPER(B65)="Y"),"",IF(C72="","",ROUNDDOWN(48/C72,0))),"") | E72: =IFERROR(IF(NOT(UPPER(B65)="Y"),"",IF(D72="","",D72*10)),"") | F72: =IFERROR(IF(NOT(UPPER(B65)="Y"),"",IF(OR(B72="",E72="",E72=0),"",B72/E72)),"") | G72: =IFERROR(IF(NOT(UPPER(B65)="Y"),"",IF(F72="","",ROUNDUP(F72,0))),"")
A73: =IFERROR(IF(A43="","",A43),"") | B73: =IFERROR(IF(B43="","",B43),"") | D73: =IFERROR(IF(NOT(UPPER(B65)="Y"),"",IF(C73="","",ROUNDDOWN(48/C73,0))),"") | E73: =IFERROR(IF(NOT(UPPER(B65)="Y"),"",IF(D73="","",D73*10)),"") | F73: =IFERROR(IF(NOT(UPPER(B65)="Y"),"",IF(OR(B73="",E73="",E73=0),"",B73/E73)),"") | G73: =IFERROR(IF(NOT(UPPER(B65)="Y"),"",IF(F73="","",ROUNDUP(F73,0))),"")
A74: =IFERROR(IF(A44="","",A44),"") | B74: =IFERROR(IF(B44="","",B44),"") | D74: =IFERROR(IF(NOT(UPPER(B65)="Y"),"",IF(C74="","",ROUNDDOWN(48/C74,0))),"") | E74: =IFERROR(IF(NOT(UPPER(B65)="Y"),"",IF(D74="","",D74*10)),"") | F74: =IFERROR(IF(NOT(UPPER(B65)="Y"),"",IF(OR(B74="",E74="",E74=0),"",B74/E74)),"") | G74: =IFERROR(IF(NOT(UPPER(B65)="Y"),"",IF(F74="","",ROUNDUP(F74,0))),"")
A75: Perimeter adjustment | D75: =IFERROR(IF(NOT(UPPER(B65)="Y"),"",IF(C75="","",ROUNDDOWN(48/C75,0))),"") | E75: =IFERROR(IF(NOT(UPPER(B65)="Y"),"",IF(D75="","",D75*10)),"") | F75: =IFERROR(IF(NOT(UPPER(B65)="Y"),"",IF(OR(B75="",E75="",E75=0),"",B75/E75)),"") | G75: =IFERROR(IF(NOT(UPPER(B65)="Y"),"",IF(F75="","",ROUNDUP(F75,0))),"") | J75: the metal perimeter from the takeoff, less what the rows above already cover
A76: TOTAL | B76: =IFERROR(IF(COUNT(C68:C75)=0,"",SUMIF(C68:C75,"<>",B68:B75)),"") | G76: =IFERROR(IF(OR(UPPER(B65)<>"Y",COUNT(G68:G75)=0),"",SUM(G68:G75)),"") | J76: LF counts only facets with a stretch-out. Everything to the right blanks out when this piece is prefab.
A78: E3 · COUNTER FLASHING
A79: Fabricate in-house? | B79: Y | J79: DEFAULTS TO Y — SMS fabricates. Change to N only when somebody else is supplying it, and say who. Never leave it N by accident: N means you do not get paid for the fab.
A80: From my takeoff (LF) | C80: =IFERROR(IF(B80="","",B80-B90),"") | D80: =IFERROR(IF(B80="","",IF(ROUND(B80-B90,2)=0,"OK","CHECK")),"") | J80: the LF this piece shows on the takeoff app — this sheet builds its own from the facets; the two should agree
A81: Piece | B81: Length (ft) | C81: Stretch-out (in) | D81: Strips | E81: Ft / sheet | F81: RAW sheets | G81: Sheets | J81: Note
A82: =IFERROR(IF(A38="","",A38),"") | B82: =IFERROR(IF(B38="","",B38),"") | D82: =IFERROR(IF(NOT(UPPER(B79)="Y"),"",IF(C82="","",ROUNDDOWN(48/C82,0))),"") | E82: =IFERROR(IF(NOT(UPPER(B79)="Y"),"",IF(D82="","",D82*10)),"") | F82: =IFERROR(IF(NOT(UPPER(B79)="Y"),"",IF(OR(B82="",E82="",E82=0),"",B82/E82)),"") | G82: =IFERROR(IF(NOT(UPPER(B79)="Y"),"",IF(F82="","",ROUNDUP(F82,0))),"")
A83: =IFERROR(IF(A39="","",A39),"") | B83: =IFERROR(IF(B39="","",B39),"") | D83: =IFERROR(IF(NOT(UPPER(B79)="Y"),"",IF(C83="","",ROUNDDOWN(48/C83,0))),"") | E83: =IFERROR(IF(NOT(UPPER(B79)="Y"),"",IF(D83="","",D83*10)),"") | F83: =IFERROR(IF(NOT(UPPER(B79)="Y"),"",IF(OR(B83="",E83="",E83=0),"",B83/E83)),"") | G83: =IFERROR(IF(NOT(UPPER(B79)="Y"),"",IF(F83="","",ROUNDUP(F83,0))),"")
A84: =IFERROR(IF(A40="","",A40),"") | B84: =IFERROR(IF(B40="","",B40),"") | D84: =IFERROR(IF(NOT(UPPER(B79)="Y"),"",IF(C84="","",ROUNDDOWN(48/C84,0))),"") | E84: =IFERROR(IF(NOT(UPPER(B79)="Y"),"",IF(D84="","",D84*10)),"") | F84: =IFERROR(IF(NOT(UPPER(B79)="Y"),"",IF(OR(B84="",E84="",E84=0),"",B84/E84)),"") | G84: =IFERROR(IF(NOT(UPPER(B79)="Y"),"",IF(F84="","",ROUNDUP(F84,0))),"")
A85: =IFERROR(IF(A41="","",A41),"") | B85: =IFERROR(IF(B41="","",B41),"") | D85: =IFERROR(IF(NOT(UPPER(B79)="Y"),"",IF(C85="","",ROUNDDOWN(48/C85,0))),"") | E85: =IFERROR(IF(NOT(UPPER(B79)="Y"),"",IF(D85="","",D85*10)),"") | F85: =IFERROR(IF(NOT(UPPER(B79)="Y"),"",IF(OR(B85="",E85="",E85=0),"",B85/E85)),"") | G85: =IFERROR(IF(NOT(UPPER(B79)="Y"),"",IF(F85="","",ROUNDUP(F85,0))),"")
A86: =IFERROR(IF(A42="","",A42),"") | B86: =IFERROR(IF(B42="","",B42),"") | D86: =IFERROR(IF(NOT(UPPER(B79)="Y"),"",IF(C86="","",ROUNDDOWN(48/C86,0))),"") | E86: =IFERROR(IF(NOT(UPPER(B79)="Y"),"",IF(D86="","",D86*10)),"") | F86: =IFERROR(IF(NOT(UPPER(B79)="Y"),"",IF(OR(B86="",E86="",E86=0),"",B86/E86)),"") | G86: =IFERROR(IF(NOT(UPPER(B79)="Y"),"",IF(F86="","",ROUNDUP(F86,0))),"")
A87: =IFERROR(IF(A43="","",A43),"") | B87: =IFERROR(IF(B43="","",B43),"") | D87: =IFERROR(IF(NOT(UPPER(B79)="Y"),"",IF(C87="","",ROUNDDOWN(48/C87,0))),"") | E87: =IFERROR(IF(NOT(UPPER(B79)="Y"),"",IF(D87="","",D87*10)),"") | F87: =IFERROR(IF(NOT(UPPER(B79)="Y"),"",IF(OR(B87="",E87="",E87=0),"",B87/E87)),"") | G87: =IFERROR(IF(NOT(UPPER(B79)="Y"),"",IF(F87="","",ROUNDUP(F87,0))),"")
A88: =IFERROR(IF(A44="","",A44),"") | B88: =IFERROR(IF(B44="","",B44),"") | D88: =IFERROR(IF(NOT(UPPER(B79)="Y"),"",IF(C88="","",ROUNDDOWN(48/C88,0))),"") | E88: =IFERROR(IF(NOT(UPPER(B79)="Y"),"",IF(D88="","",D88*10)),"") | F88: =IFERROR(IF(NOT(UPPER(B79)="Y"),"",IF(OR(B88="",E88="",E88=0),"",B88/E88)),"") | G88: =IFERROR(IF(NOT(UPPER(B79)="Y"),"",IF(F88="","",ROUNDUP(F88,0))),"")
A89: Perimeter adjustment | D89: =IFERROR(IF(NOT(UPPER(B79)="Y"),"",IF(C89="","",ROUNDDOWN(48/C89,0))),"") | E89: =IFERROR(IF(NOT(UPPER(B79)="Y"),"",IF(D89="","",D89*10)),"") | F89: =IFERROR(IF(NOT(UPPER(B79)="Y"),"",IF(OR(B89="",E89="",E89=0),"",B89/E89)),"") | G89: =IFERROR(IF(NOT(UPPER(B79)="Y"),"",IF(F89="","",ROUNDUP(F89,0))),"") | J89: the metal perimeter from the takeoff, less what the rows above already cover
A90: TOTAL | B90: =IFERROR(IF(COUNT(C82:C89)=0,"",SUMIF(C82:C89,"<>",B82:B89)),"") | G90: =IFERROR(IF(OR(UPPER(B79)<>"Y",COUNT(G82:G89)=0),"",SUM(G82:G89)),"") | J90: LF counts only facets with a stretch-out. Everything to the right blanks out when this piece is prefab.
A92: E4 · DOWNSPOUTS & GUTTERS — straight from the takeoff, one line each
A93: Piece | B93: LF | C93: Stretch-out (in) | D93: Strips | E93: Ft / sheet | F93: RAW sheets | G93: Sheets | H93: Fabricate? | I93: If N — who supplies | J93: Note
A94: Downspouts | D94: =IFERROR(IF(UPPER(H94)<>"Y","",IF(C94="","",ROUNDDOWN(48/C94,0))),"") | E94: =IFERROR(IF(UPPER(H94)<>"Y","",IF(D94="","",D94*10)),"") | F94: =IFERROR(IF(UPPER(H94)<>"Y","",IF(OR(B94="",E94="",E94=0),"",B94/E94)),"") | G94: =IFERROR(IF(OR(F94="",UPPER(H94)<>"Y"),"",ROUNDUP(F94,0)),"") | H94: Y | J94: DEFAULTS TO Y — SMS fabricates.
A95: Gutters | D95: =IFERROR(IF(UPPER(H95)<>"Y","",IF(C95="","",ROUNDDOWN(48/C95,0))),"") | E95: =IFERROR(IF(UPPER(H95)<>"Y","",IF(D95="","",D95*10)),"") | F95: =IFERROR(IF(UPPER(H95)<>"Y","",IF(OR(B95="",E95="",E95=0),"",B95/E95)),"") | G95: =IFERROR(IF(OR(F95="",UPPER(H95)<>"Y"),"",ROUNDUP(F95,0)),"") | H95: Y
A97: TOTAL SHEETS TO FABRICATE | G97: =IFERROR(IF((N(G62)+N(G76)+N(G90)+N(G94)+N(G95))=0,"",(N(G62)+N(G76)+N(G90)+N(G94)+N(G95))),"")
A99: E5 · CLEATS — all of them, in one place
A100: "A cleat is its own metal, its own stretch-out, its own sheets — and we fabricate cleats in-house, same as the metal. COPING ALWAYS GETS ONE — 100% of the time — and its cleat runs the same stretch-out as the coping itself. GRAVEL STOP: ask every job, Y or N. COUNTER FLASHING: never gets one."
A101: Piece | B101: LF | C101: Cleat? | D101: Face (in) | E101: Cleat stretch-out (in) | F101: Ft / sheet | G101: Sheets | J101: Note
A102: Coping cleat | B102: =IFERROR(B62,"") | C102: Y | E102: =IFERROR(IF(MAX(C54:C61)=0,"",MAX(C54:C61)),"") | F102: =IFERROR(IF(E102="","",ROUNDDOWN(48/E102,0)*10),"") | G102: =IFERROR(IF(UPPER(B51)<>"Y","",IF(OR(UPPER(C102)<>"Y",F102="",F102=0),"",ROUNDUP(B102/F102,0))),"") | H102: =IFERROR(IF(UPPER(B51)<>"Y","n/a — that piece is not fabricated here",""),"") | J102: LAW — always, and the cleat runs the SAME stretch-out as the coping.
A103: Gravel stop cleat | B103: =IFERROR(B76,"") | C103: Y | F103: =IFERROR(IF(E103="","",ROUNDDOWN(48/E103,0)*10),"") | G103: =IFERROR(IF(UPPER(B65)<>"Y","",IF(OR(UPPER(C103)<>"Y",F103="",F103=0),"",ROUNDUP(B103/F103,0))),"") | H103: =IFERROR(IF(UPPER(B65)<>"Y","n/a — that piece is not fabricated here",""),"") | I103: Gravel stop gets a cleat on this job — 9.6 in stretch-out. Houston: the gravel stop face is 12 in, which is not big in real life. | J103: needs a cleat at a face over 3½″ of face. Blanks out if the piece is prefab.
A105: TOTAL CLEAT SHEETS | G105: =IFERROR(IF(COUNT(G102:G103)=0,"",SUMPRODUCT(N(G102:G103))),"")
A106: TOTAL SHEETS TO FABRICATE (metal + cleats) | G106: =IFERROR(IF((N(G62)+N(G76)+N(G90)+N(G94)+N(G95)+N(G105))=0,"",(N(G62)+N(G76)+N(G90)+N(G94)+N(G95)+N(G105))),"")
A108: F · CHECKS & BALANCES
A109: "Every check here was stated by Adam. None are invented. Blank rows are for checks he adds later — do not fill them."
A110: Check | B110: This sheet | C110: Takeoff app | D110: Difference | E110: % | F110: Tolerance % | G110: Status | J110: Note
...

Sheet Material Order
A1: MATERIAL ORDER — MECHANICALLY ATTACHED TPO
A2: PAGE THREE. Every quantity reads live off the Material Takeoff page. RAW is the number before it rounds up. Prices are yours to set — nothing here is priced by me. The purchased block is what goes to the supplier.
A4: PURCHASED (send to supplier)
A5: Item | B5: RAW (before rounding) | C5: Qty | D5: Unit | E5: Unit $ | F5: Line Total
A6: TPO field membrane 10' | B6: =IFERROR(IF('Material Takeoff'!F28="","",'Material Takeoff'!F28),"") | C6: =IFERROR(IF('Material Takeoff'!G28="","",'Material Takeoff'!G28),"") | D6: roll | E6: =IF(OR(C6="NA",C6="",N(C6)=0),"",IFERROR(IF(VLOOKUP($A6,'Bid Products'!$A$4:$D$60,4,FALSE())="","",VLOOKUP($A6,'Bid Products'!$A$4:$D$60,4,FALSE())),"")) | F6: =IF(OR(C6="NA",C6="",E6=""),"",C6*E6)
A7: ="10 ft roll = 10 squares. 6 in. of it gets lapped over, so 5% is gone, plus "&TEXT('Material Takeoff'!D28,"0%")&" for cuts. Interior "&TEXT(N('Material Takeoff'!B28),"0")&" sq x "&TEXT('Material Takeoff'!E28,"0.00")&" ÷ 10 = "&TEXT(N('Material Takeoff'!G28),"0")&" rolls."
A8: TPO field membrane 5' | B8: =IFERROR(IF('Material Takeoff'!F29="","",'Material Takeoff'!F29),"") | C8: =IFERROR(IF('Material Takeoff'!G29="","",'Material Takeoff'!G29),"") | D8: roll | E8: =IF(OR(C8="NA",C8="",N(C8)=0),"",IFERROR(IF(VLOOKUP($A8,'Bid Products'!$A$4:$D$60,4,FALSE())="","",VLOOKUP($A8,'Bid Products'!$A$4:$D$60,4,FALSE())),"")) | F8: =IF(OR(C8="NA",C8="",E8=""),"",C8*E8)
A9: ="5 ft roll = 5 squares. 6 in. of it gets lapped over, so 10% is gone, plus "&TEXT('Material Takeoff'!D29,"0%")&" for cuts. Perimeter "&TEXT(N('Material Takeoff'!B29),"0")&" sq x "&TEXT('Material Takeoff'!E29,"0.00")&" ÷ 5 = "&TEXT(N('Material Takeoff'!G29),"0")&" rolls."
A10: TPO wall membrane 5' | B10: =IFERROR(IF('Material Takeoff'!F30="","",'Material Takeoff'!F30),"") | C10: =IFERROR(IF('Material Takeoff'!G30="","",'Material Takeoff'!G30),"") | D10: roll | E10: =IF(OR(C10="NA",C10="",N(C10)=0),"",IFERROR(IF(VLOOKUP("TPO wall membrane 5'",'Bid Products'!$A$4:$D$60,4,FALSE())="","",VLOOKUP("TPO wall membrane 5'",'Bid Products'!$A$4:$D$60,4,FALSE())),"")) | F10: =IF(OR(C10="NA",C10="",E10=""),"",C10*E10)
A11: ="Same 5 ft roll. Walls take "&TEXT('Material Takeoff'!D30,"0%")&" for cuts. Walls "&TEXT(N('Material Takeoff'!B30),"0")&" sq x "&TEXT('Material Takeoff'!E30,"0.00")&" ÷ 5 = "&TEXT(N('Material Takeoff'!G30),"0")&" rolls."
A12: Polyiso — field of the roof | B12: =IFERROR(IF('Material Takeoff'!F14="","",'Material Takeoff'!F14),"") | C12: =IFERROR(IF('Material Takeoff'!G14="","",'Material Takeoff'!G14),"") | D12: board | E12: =IF(OR(C12="NA",C12="",N(C12)=0),"",IFERROR(IF(VLOOKUP($A12,'Bid Products'!$A$4:$D$60,4,FALSE())="","",VLOOKUP($A12,'Bid Products'!$A$4:$D$60,4,FALSE())),"")) | F12: =IF(OR(C12="NA",C12="",E12=""),"",C12*E12)
A13: ="3 boards a square. Flat — no waste added. "&TEXT(N('Material Takeoff'!B14),"0")&" sq x 3 = "&TEXT(N('Material Takeoff'!G14),"0")&" boards"
A15: Crickets — Units · Q board | B15: =IFERROR(IF('Material Takeoff'!B22="","",'Material Takeoff'!B22),"") | C15: =IFERROR(IF('Material Takeoff'!G22="","",'Material Takeoff'!G22),"") | D15: board | E15: =IF(OR(C15="NA",C15="",N(C15)=0),"",IFERROR(IF(VLOOKUP($A15,'Bid Products'!$A$4:$D$60,4,FALSE())="","",VLOOKUP($A15,'Bid Products'!$A$4:$D$60,4,FALSE())),"")) | F15: =IF(OR(C15="NA",C15="",E15=""),"",C15*E15)
A16: ="52 unit curbs x 4 corners = "&TEXT(N(Takeoff!F22)*4,"0")&" corners. Check that against the TPO corners line below — the two have to agree. Pull this line and the unit crickets come out of the quote."
A17: Crickets — Scuppers / Drains · Q board | B17: =IFERROR(IF('Material Takeoff'!B23="","",'Material Takeoff'!B23),"") | C17: =IFERROR(IF('Material Takeoff'!G23="","",'Material Takeoff'!G23),"") | D17: board | E17: =IF(OR(C17="NA",C17="",N(C17)=0),"",IFERROR(IF(VLOOKUP($A17,'Bid Products'!$A$4:$D$60,4,FALSE())="","",VLOOKUP($A17,'Bid Products'!$A$4:$D$60,4,FALSE())),"")) | F17: =IF(OR(C17="NA",C17="",E17=""),"",C17*E17)
A18: Crickets — Scuppers / Drains · 2″ fill board 4 ft x 4 ft | B18: =IFERROR(IF('Material Takeoff'!D23="","",'Material Takeoff'!D23),"") | C18: =IFERROR(IF('Material Takeoff'!D23="","",'Material Takeoff'!D23),"") | D18: board | E18: =IF(OR(C18="NA",C18="",N(C18)=0),"",IFERROR(IF(VLOOKUP($A18,'Bid Products'!$A$4:$D$60,4,FALSE())="","",VLOOKUP($A18,'Bid Products'!$A$4:$D$60,4,FALSE())),"")) | F18: =IF(OR(C18="NA",C18="",E18=""),"",C18*E18)
A19: ="7 crickets that steer water to the scuppers and drains — "&TEXT(N('Material Takeoff'!B23),"0")&" Q board plus "&TEXT(N('Material Takeoff'!D23),"0")&" pieces of 2″ fill at 4 ft x 4 ft. These have to be there."
A21: FASTENERS & PLATES
A22: Item | B22: RAW (before rounding) | C22: Qty | D22: Unit | E22: Unit $ | F22: Line Total
A23: ISO plates | B23: =IFERROR(IF('Material Takeoff'!F41="","",'Material Takeoff'!F41),"") | C23: =IFERROR(IF('Material Takeoff'!G41="","",'Material Takeoff'!G41),"") | D23: box | E23: =IF(OR(C23="NA",C23="",N(C23)=0),"",IFERROR(IF(VLOOKUP("ISO plates",'Bid Products'!$A$4:$D$60,4,FALSE())="","",VLOOKUP("ISO plates",'Bid Products'!$A$4:$D$60,4,FALSE())),"")) | F23: =IF(OR(C23="NA",C23="",E23=""),"",C23*E23)
A24: Seam plates | B24: =IFERROR(IF('Material Takeoff'!F82="","",'Material Takeoff'!F82),"") | C24: =IFERROR(IF('Material Takeoff'!G82="","",'Material Takeoff'!G82),"") | D24: box | E24: =IF(OR(C24="NA",C24="",N(C24)=0),"",IFERROR(IF(VLOOKUP("Seam plates",'Bid Products'!$A$4:$D$60,4,FALSE())="","",VLOOKUP("Seam plates",'Bid Products'!$A$4:$D$60,4,FALSE())),"")) | F24: =IF(OR(C24="NA",C24="",E24=""),"",C24*E24)
A25: ="Rolls x 100, plus curb, boots x 4, pans x 4, wall rows and base flashing. All of it x 1.1 = "&TEXT(N('Material Takeoff'!F82),"#,##0")&" plates. One plate, one buy."
A26: TOTAL FASTENERS | B26: =IFERROR(IF('Material Takeoff'!F91="","",'Material Takeoff'!F91),"") | F26: =IF(OR(C26="NA",C26="",E26=""),"",C26*E26)
A27: Insulation fasteners #12 | B27: =IFERROR(IF('Material Takeoff'!F87="","",'Material Takeoff'!F87),"") | C27: =IFERROR(IF('Material Takeoff'!G87="","",'Material Takeoff'!G87),"") | D27: box | E27: =IF(OR(C27="NA",C27="",N(C27)=0),"",IFERROR(IF(VLOOKUP("Insulation fasteners #12",'Bid Products'!$A$4:$D$60,4,FALSE())="","",VLOOKUP("Insulation fasteners #12",'Bid Products'!$A$4:$D$60,4,FALSE())),"")) | F27: =IF(OR(C27="NA",C27="",E27=""),"",C27*E27)
A28: ="One screw per ISO plate. "&TEXT(N('Material Takeoff'!B41),"#,##0")&" boards x "&TEXT(N(Takeoff!B14),"0")&" plates a board = "&TEXT(N('Material Takeoff'!F41),"#,##0")&" screws — #"&TEXT(N('Material Takeoff'!B36),"0")&" x "&TEXT(N('Material Takeoff'!B35),"0")&" in."
A29: Seam fasteners #15 — 5" | B29: =IFERROR(IF('Material Takeoff'!F88="","",'Material Takeoff'!F88),"") | C29: =IFERROR(IF('Material Takeoff'!G88="","",'Material Takeoff'!G88),"") | D29: box | E29: =IF(OR(C29="NA",C29="",N(C29)=0),"",IFERROR(IF(VLOOKUP("Seam fasteners #15 — 5""",'Bid Products'!$A$4:$D$60,4,FALSE())="","",VLOOKUP("Seam fasteners #15 — 5""",'Bid Products'!$A$4:$D$60,4,FALSE())),"")) | F29: =IF(OR(C29="NA",C29="",E29=""),"",C29*E29)
A30: ="One screw per seam plate. "&TEXT(IF(ISNUMBER(SEARCH("WOOD",UPPER(Takeoff!L38))),N('Material Takeoff'!F80),N('Material Takeoff'!F82)),"#,##0")&" screws called for, less the "&TEXT(N('Material Takeoff'!F89)+N('Material Takeoff'!F90),"#,##0")&" that go long = "&TEXT(N('Material Takeoff'!F88),"#,##0")&" at 5 in."
A31: Seam fasteners #15 — 7" | B31: =IFERROR(IF('Material Takeoff'!F89="","",'Material Takeoff'!F89),"") | C31: =IFERROR(IF('Material Takeoff'!G89="","",'Material Takeoff'!G89),"") | D31: box | E31: =IF(OR(C31="NA",C31="",N(C31)=0),"",IFERROR(IF(VLOOKUP("Seam fasteners #15 — 7""",'Bid Products'!$A$4:$D$60,4,FALSE())="","",VLOOKUP("Seam fasteners #15 — 7""",'Bid Products'!$A$4:$D$60,4,FALSE())),"")) | F31: =IF(OR(C31="NA",C31="",E31=""),"",C31*E31)
A32: ="For the crickets. This box came OUT of the 5 in. count, not on top of it — the crickets build the insulation up and a 5 in. screw stops short."
A33: Seam fasteners #15 — 8" | B33: =IFERROR(IF('Material Takeoff'!F90="","",'Material Takeoff'!F90),"") | C33: =IFERROR(IF('Material Takeoff'!G90="","",'Material Takeoff'!G90),"") | D33: box | E33: =IF(OR(C33="NA",C33="",N(C33)=0),"",IFERROR(IF(VLOOKUP("Seam fasteners #15 — 8""",'Bid Products'!$A$4:$D$60,4,FALSE())="","",VLOOKUP("Seam fasteners #15 — 8""",'Bid Products'!$A$4:$D$60,4,FALSE())),"")) | F33: =IF(OR(C33="NA",C33="",E33=""),"",C33*E33)
A34: ="Same — out of the 5 in. count, for the deepest part of the crickets."
A36: ADHESIVES
A37: Item | B37: RAW (before rounding) | C37: Qty | D37: Unit | E37: Unit $ | F37: Line Total
A38: Bonding adhesive | B38: =IFERROR(IF('Material Takeoff'!F97="","",'Material Takeoff'!F97),"") | C38: =IFERROR(IF('Material Takeoff'!G97="","",'Material Takeoff'!G97),"") | D38: pail | E38: =IF(OR(C38="NA",C38="",N(C38)=0),"",IFERROR(IF(VLOOKUP("Bonding adhesive",'Bid Products'!$A$4:$D$60,4,FALSE())="","",VLOOKUP("Bonding adhesive",'Bid Products'!$A$4:$D$60,4,FALSE())),"")) | F38: =IF(OR(C38="NA",C38="",E38=""),"",C38*E38)
A39: ="Wall squares plus the curb, ÷ 3. Curb is "&TEXT(N(Takeoff!B26),"#,##0")&" ft x "&TEXT(N('Material Takeoff'!B94),"0")&" ft tall = "&TEXT(N(Takeoff!B26)*N('Material Takeoff'!B94),"#,##0")&" sf. "&TEXT(N('Material Takeoff'!G8),"0")&" sq + "&TEXT(N(Takeoff!B26)*N('Material Takeoff'!B94)/100,"0.00")&" sq ÷ 3 = "&TEXT(N('Material Takeoff'!G97),"0")&" pails"
A40: Rollers | B40: =IFERROR(IF('Material Takeoff'!F108="","",'Material Takeoff'!F108),"") | C40: =IFERROR(IF('Material Takeoff'!G108="","",'Material Takeoff'!G108),"") | D40: ea | E40: =IF(OR(C40="NA",C40="",N(C40)=0),"",IFERROR(IF(VLOOKUP("Rollers",'Bid Products'!$A$4:$D$60,4,FALSE())="","",VLOOKUP("Rollers",'Bid Products'!$A$4:$D$60,4,FALSE())),"")) | F40: =IF(OR(C40="NA",C40="",E40=""),"",C40*E40)
A41: =IF(N('Material Takeoff'!D108)=0,"rule not set yet",IF(RIGHT('Material Takeoff'!E108,1)=".",'Material Takeoff'!E108,'Material Takeoff'!E108&".")&" "&TEXT(N('Material Takeoff'!B108),"#,##0.##")&" ÷ "&TEXT(N('Material Takeoff'!D108),"#,##0.##")&" = "&TEXT(N('Material Takeoff'!G108),"#,##0")&" ea")
A42: Cages | B42: =IFERROR(IF('Material Takeoff'!F109="","",'Material Takeoff'!F109),"") | C42: =IFERROR(IF('Material Takeoff'!G109="","",'Material Takeoff'!G109),"") | D42: ea | E42: =IF(OR(C42="NA",C42="",N(C42)=0),"",IFERROR(IF(VLOOKUP("Cages",'Bid Products'!$A$4:$D$60,4,FALSE())="","",VLOOKUP("Cages",'Bid Products'!$A$4:$D$60,4,FALSE())),"")) | F42: =IF(OR(C42="NA",C42="",E42=""),"",C42*E42)
A43: =IF(N('Material Takeoff'!D109)=0,"rule not set yet",IF(RIGHT('Material Takeoff'!E109,1)=".",'Material Takeoff'!E109,'Material Takeoff'!E109&".")&" "&TEXT(N('Material Takeoff'!B109),"#,##0.##")&" ÷ "&TEXT(N('Material Takeoff'!D109),"#,##0.##")&" = "&TEXT(N('Material Takeoff'!G109),"#,##0")&" ea")
A44: Sticks | B44: =IFERROR(IF('Material Takeoff'!F110="","",'Material Takeoff'!F110),"") | C44: =IFERROR(IF('Material Takeoff'!G110="","",'Material Takeoff'!G110),"") | D44: ea | E44: =IF(OR(C44="NA",C44="",N(C44)=0),"",IFERROR(IF(VLOOKUP("Sticks",'Bid Products'!$A$4:$D$60,4,FALSE())="","",VLOOKUP("Sticks",'Bid Products'!$A$4:$D$60,4,FALSE())),"")) | F44: =IF(OR(C44="NA",C44="",E44=""),"",C44*E44)
A45: =IF(N('Material Takeoff'!D110)=0,"rule not set yet",IF(RIGHT('Material Takeoff'!E110,1)=".",'Material Takeoff'!E110,'Material Takeoff'!E110&".")&" "&TEXT(N('Material Takeoff'!B110),"#,##0.##")&" ÷ "&TEXT(N('Material Takeoff'!D110),"#,##0.##")&" = "&TEXT(N('Material Takeoff'!G110),"#,##0")&" ea")
A46: ACCESSORIES
A47: Item | B47: RAW (before rounding) | C47: Qty | D47: Unit | E47: Unit $ | F47: Line Total
A48: Unsupported flashing | B48: =IFERROR(IF('Material Takeoff'!F98="","",'Material Takeoff'!F98),"") | C48: =IFERROR(IF('Material Takeoff'!G98="","",'Material Takeoff'!G98),"") | D48: roll | E48: =IF(OR(C48="NA",C48="",N(C48)=0),"",IFERROR(IF(VLOOKUP("Unsupported flashing",'Bid Products'!$A$4:$D$60,4,FALSE())="","",VLOOKUP("Unsupported flashing",'Bid Products'!$A$4:$D$60,4,FALSE())),"")) | F48: =IF(OR(C48="NA",C48="",E48=""),"",C48*E48)
A49: =IF(N('Material Takeoff'!D98)=0,"rule not set yet",IF(RIGHT('Material Takeoff'!E98,1)=".",'Material Takeoff'!E98,'Material Takeoff'!E98&".")&" "&TEXT(N('Material Takeoff'!B98),"#,##0.##")&" ÷ "&TEXT(N('Material Takeoff'!D98),"#,##0.##")&" = "&TEXT(N('Material Takeoff'!G98),"#,##0")&" roll")
A50: TPO T-joints | B50: =IFERROR(IF('Material Takeoff'!F100="","",'Material Takeoff'!F100),"") | C50: =IFERROR(IF('Material Takeoff'!G100="","",'Material Takeoff'!G100),"") | D50: bag | E50: =IF(OR(C50="NA",C50="",N(C50)=0),"",IFERROR(IF(VLOOKUP("TPO T-joints",'Bid Products'!$A$4:$D$60,4,FALSE())="","",VLOOKUP("TPO T-joints",'Bid Products'!$A$4:$D$60,4,FALSE())),"")) | F50: =IF(OR(C50="NA",C50="",E50=""),"",C50*E50)
A51: =IF(N('Material Takeoff'!D100)=0,"rule not set yet",IF(RIGHT('Material Takeoff'!E100,1)=".",'Material Takeoff'!E100,'Material Takeoff'!E100&".")&" "&TEXT(N('Material Takeoff'!B100),"#,##0.##")&" ÷ "&TEXT(N('Material Takeoff'!D100),"#,##0.##")&" = "&TEXT(N('Material Takeoff'!G100),"#,##0")&" box")
A52: TPO corners | B52: =IFERROR(IF('Material Takeoff'!F114="","",'Material Takeoff'!F114),"") | C52: =IFERROR(IF('Material Takeoff'!G114="","",'Material Takeoff'!G114),"") | D52: ea | E52: =IF(OR(C52="NA",C52="",N(C52)=0),"",IFERROR(IF(VLOOKUP("TPO corners",'Bid Products'!$A$4:$D$60,4,FALSE())="","",VLOOKUP("TPO corners",'Bid Products'!$A$4:$D$60,4,FALSE())),"")) | F52: =IF(OR(C52="NA",C52="",E52=""),"",C52*E52)
A53: ="4 corners on every curb. "&TEXT(N(Takeoff!F22),"#,##0")&" curbs x 4 = "&TEXT(N('Material Takeoff'!G114),"#,##0")&" corners. Unsupported flashing stays in for the odd details."
A54: TPO molded pipe boots | B54: =IFERROR(C54,"") | C54: =IFERROR(N(Takeoff!B28),"") | D54: ea | E54: =IF(OR(C54="NA",C54="",N(C54)=0),"",IFERROR(IF(VLOOKUP("TPO molded pipe boots",'Bid Products'!$A$4:$D$60,4,FALSE())="","",VLOOKUP("TPO molded pipe boots",'Bid Products'!$A$4:$D$60,4,FALSE())),"")) | F54: =IF(OR(C54="NA",C54="",E54=""),"",C54*E54)
A55: Pitch pockets | B55: =IFERROR(C55,"") | C55: =IFERROR(N(Takeoff!B27),"") | D55: ea | E55: =IF(OR(C55="NA",C55="",N(C55)=0),"",IFERROR(IF(VLOOKUP("Pitch pockets",'Bid Products'!$A$4:$D$60,4,FALSE())="","",VLOOKUP("Pitch pockets",'Bid Products'!$A$4:$D$60,4,FALSE())),"")) | F55: =IF(OR(C55="NA",C55="",E55=""),"",C55*E55)
A56: Pourable sealer | B56: =IFERROR(N(Takeoff!B27)/2,"") | C56: =IFERROR(IF(N(Takeoff!B27)=0,"",ROUNDUP(N(Takeoff!B27)/2,0)),"") | D56: kit | E56: =IF(OR(C56="NA",C56="",N(C56)=0),"",IFERROR(IF(VLOOKUP("Pourable sealer",'Bid Products'!$A$4:$D$60,4,FALSE())="","",VLOOKUP("Pourable sealer",'Bid Products'!$A$4:$D$60,4,FALSE())),"")) | F56: =IF(OR(C56="NA",C56="",E56=""),"",C56*E56)
A57: TPO cover tape | B57: =IFERROR(IF('Material Takeoff'!F113="","",'Material Takeoff'!F113),"") | C57: =IFERROR(IF('Material Takeoff'!G113="","",'Material Takeoff'!G113),"") | D57: roll | E57: =IF(OR(C57="NA",C57="",N(C57)=0),"",IFERROR(IF(VLOOKUP("TPO cover tape",'Bid Products'!$A$4:$D$60,4,FALSE())="","",VLOOKUP("TPO cover tape",'Bid Products'!$A$4:$D$60,4,FALSE())),"")) | F57: =IF(OR(C57="NA",C57="",E57=""),"",C57*E57)
A58: =IF(N('Material Takeoff'!D113)=0,"rule not set yet",IF(RIGHT('Material Takeoff'!E113,1)=".",'Material Takeoff'!E113,'Material Takeoff'!E113&".")&" "&TEXT(N('Material Takeoff'!B113),"#,##0.##")&" ÷ "&TEXT(N('Material Takeoff'!D113),"#,##0.##")&" = "&TEXT(N('Material Takeoff'!G113),"#,##0")&" roll")
A59: Primer | B59: =IFERROR(IF('Material Takeoff'!F111="","",'Material Takeoff'!F111),"") | C59: =IFERROR(IF('Material Takeoff'!G111="","",'Material Takeoff'!G111),"") | D59: pail | E59: =IF(OR(C59="NA",C59="",N(C59)=0),"",IFERROR(IF(VLOOKUP("Primer",'Bid Products'!$A$4:$D$60,4,FALSE())="","",VLOOKUP("Primer",'Bid Products'!$A$4:$D$60,4,FALSE())),"")) | F59: =IF(OR(C59="NA",C59="",E59=""),"",C59*E59)
A60: =IF(N('Material Takeoff'!D111)=0,"rule not set yet",IF(RIGHT('Material Takeoff'!E111,1)=".",'Material Takeoff'!E111,'Material Takeoff'!E111&".")&" "&TEXT(N('Material Takeoff'!B111),"#,##0.##")&" ÷ "&TEXT(N('Material Takeoff'!D111),"#,##0.##")&" = "&TEXT(N('Material Takeoff'!G111),"#,##0")&" can")
A61: Brushes | B61: =IFERROR(IF('Material Takeoff'!F112="","",'Material Takeoff'!F112),"") | C61: =IFERROR(IF('Material Takeoff'!G112="","",'Material Takeoff'!G112),"") | D61: ea | E61: =IF(OR(C61="NA",C61="",N(C61)=0),"",IFERROR(IF(VLOOKUP("Brushes",'Bid Products'!$A$4:$D$60,4,FALSE())="","",VLOOKUP("Brushes",'Bid Products'!$A$4:$D$60,4,FALSE())),"")) | F61: =IF(OR(C61="NA",C61="",E61=""),"",C61*E61)
A62: =IF(N('Material Takeoff'!D112)=0,"rule not set yet",IF(RIGHT('Material Takeoff'!E112,1)=".",'Material Takeoff'!E112,'Material Takeoff'!E112&".")&" "&TEXT(N('Material Takeoff'!B112),"#,##0.##")&" ÷ "&TEXT(N('Material Takeoff'!D112),"#,##0.##")&" = "&TEXT(N('Material Takeoff'!G112),"#,##0")&" ea")
A63: TPO cut-edge sealant | B63: =IFERROR(IF('Material Takeoff'!F101="","",'Material Takeoff'!F101),"") | C63: =IFERROR(IF('Material Takeoff'!G101="","",'Material Takeoff'!G101),"") | D63: tube | E63: =IF(OR(C63="NA",C63="",N(C63)=0),"",IFERROR(IF(VLOOKUP("TPO cut-edge sealant",'Bid Products'!$A$4:$D$60,4,FALSE())="","",VLOOKUP("TPO cut-edge sealant",'Bid Products'!$A$4:$D$60,4,FALSE())),"")) | F63: =IF(OR(C63="NA",C63="",E63=""),"",C63*E63)
A64: =IF(N('Material Takeoff'!D101)=0,"rule not set yet",IF(RIGHT('Material Takeoff'!E101,1)=".",'Material Takeoff'!E101,'Material Takeoff'!E101&".")&" "&TEXT(N('Material Takeoff'!B101),"#,##0.##")&" ÷ "&TEXT(N('Material Takeoff'!D101),"#,##0.##")&" = "&TEXT(N('Material Takeoff'!G101),"#,##0")&" tube")
A65: TPO LVOC all-purpose | B65: =IFERROR(IF('Material Takeoff'!F102="","",'Material Takeoff'!F102),"") | C65: =IFERROR(IF('Material Takeoff'!G102="","",'Material Takeoff'!G102),"") | D65: can | E65: =IF(OR(C65="NA",C65="",N(C65)=0),"",IFERROR(IF(VLOOKUP("TPO LVOC all-purpose",'Bid Products'!$A$4:$D$60,4,FALSE())="","",VLOOKUP("TPO LVOC all-purpose",'Bid Products'!$A$4:$D$60,4,FALSE())),"")) | F65: =IF(OR(C65="NA",C65="",E65=""),"",C65*E65)
A66: =IF(N('Material Takeoff'!D102)=0,"rule not set yet",IF(RIGHT('Material Takeoff'!E102,1)=".",'Material Takeoff'!E102,'Material Takeoff'!E102&".")&" "&TEXT(N('Material Takeoff'!B102),"#,##0.##")&" ÷ "&TEXT(N('Material Takeoff'!D102),"#,##0.##")&" = "&TEXT(N('Material Takeoff'!G102),"#,##0")&" can")
A67: Water block | B67: =IFERROR(IF('Material Takeoff'!F103="","",'Material Takeoff'!F103),"") | C67: =IFERROR(IF('Material Takeoff'!G103="","",'Material Takeoff'!G103),"") | D67: tube | E67: =IF(OR(C67="NA",C67="",N(C67)=0),"",IFERROR(IF(VLOOKUP("Water block",'Bid Products'!$A$4:$D$60,4,FALSE())="","",VLOOKUP("Water block",'Bid Products'!$A$4:$D$60,4,FALSE())),"")) | F67: =IF(OR(C67="NA",C67="",E67=""),"",C67*E67)
A68: =IF(N('Material Takeoff'!D103)=0,"rule not set yet",IF(RIGHT('Material Takeoff'!E103,1)=".",'Material Takeoff'!E103,'Material Takeoff'!E103&".")&" "&TEXT(N('Material Takeoff'!B103),"#,##0.##")&" ÷ "&TEXT(N('Material Takeoff'!D103),"#,##0.##")&" = "&TEXT(N('Material Takeoff'!G103),"#,##0")&" tube")
A70: TPO cleaner 5g | B70: =IFERROR(IF('Material Takeoff'!F99="","",'Material Takeoff'!F99),"") | C70: =IFERROR(IF('Material Takeoff'!G99="","",'Material Takeoff'!G99),"") | D70: pail | E70: =IF(OR(C70="NA",C70="",N(C70)=0),"",IFERROR(IF(VLOOKUP("TPO cleaner 5g",'Bid Products'!$A$4:$D$60,4,FALSE())="","",VLOOKUP("TPO cleaner 5g",'Bid Products'!$A$4:$D$60,4,FALSE())),"")) | F70: =IF(OR(C70="NA",C70="",E70=""),"",C70*E70)
A71: =IF(N('Material Takeoff'!D99)=0,"rule not set yet",IF(RIGHT('Material Takeoff'!E99,1)=".",'Material Takeoff'!E99,'Material Takeoff'!E99&".")&" "&TEXT(N('Material Takeoff'!B99),"#,##0.##")&" ÷ "&TEXT(N('Material Takeoff'!D99),"#,##0.##")&" = "&TEXT(N('Material Takeoff'!G99),"#,##0")&" can")
A72: Rags | B72: =IFERROR(IF('Material Takeoff'!F105="","",'Material Takeoff'!F105),"") | C72: =IFERROR(IF('Material Takeoff'!G105="","",'Material Takeoff'!G105),"") | D72: box | E72: =IF(OR(C72="NA",C72="",N(C72)=0),"",IFERROR(IF(VLOOKUP("Rags",'Bid Products'!$A$4:$D$60,4,FALSE())="","",VLOOKUP("Rags",'Bid Products'!$A$4:$D$60,4,FALSE())),"")) | F72: =IF(OR(C72="NA",C72="",E72=""),"",C72*E72)
A73: =IF(N('Material Takeoff'!D105)=0,"rule not set yet",IF(RIGHT('Material Takeoff'!E105,1)=".",'Material Takeoff'!E105,'Material Takeoff'!E105&".")&" "&TEXT(N('Material Takeoff'!B105),"#,##0.##")&" ÷ "&TEXT(N('Material Takeoff'!D105),"#,##0.##")&" = "&TEXT(N('Material Takeoff'!G105),"#,##0")&" box")
A74: Hose clamps | B74: =IFERROR(IF('Material Takeoff'!F106="","",'Material Takeoff'!F106),"") | C74: =IFERROR(IF('Material Takeoff'!G106="","",'Material Takeoff'!G106),"") | D74: roll | E74: =IF(OR(C74="NA",C74="",N(C74)=0),"",IFERROR(IF(VLOOKUP("Hose clamps",'Bid Products'!$A$4:$D$60,4,FALSE())="","",VLOOKUP("Hose clamps",'Bid Products'!$A$4:$D$60,4,FALSE())),"")) | F74: =IF(OR(C74="NA",C74="",E74=""),"",C74*E74)
A75: =IF(N('Material Takeoff'!D106)=0,"rule not set yet",IF(RIGHT('Material Takeoff'!E106,1)=".",'Material Takeoff'!E106,'Material Takeoff'!E106&".")&" "&TEXT(N('Material Takeoff'!B106),"#,##0.##")&" ÷ "&TEXT(N('Material Takeoff'!D106),"#,##0.##")&" = "&TEXT(N('Material Takeoff'!G106),"#,##0")&" box")
A76: Retro drains | B76: =IFERROR(IF('Material Takeoff'!F107="","",'Material Takeoff'!F107),"") | C76: =IFERROR(IF('Material Takeoff'!G107="","",'Material Takeoff'!G107),"") | D76: ea | E76: =IF(OR(C76="NA",C76="",N(C76)=0),"",IFERROR(IF(VLOOKUP("Retro drains",'Bid Products'!$A$4:$D$60,4,FALSE())="","",VLOOKUP("Retro drains",'Bid Products'!$A$4:$D$60,4,FALSE())),"")) | F76: =IF(OR(C76="NA",C76="",E76=""),"",C76*E76)
A77: =IF(ISNUMBER(SEARCH("TEAR",UPPER(Existing!B6))),"One retro drain per existing drain. "&TEXT(N(Takeoff!B34),"0")&" drains on this roof = "&TEXT(N('Material Takeoff'!G107),"0")&" retro drains. Each one takes water block, which is why the water block count is the LVOC cans plus the drains.","NEW CONSTRUCTION — a retro drain is never an option here. This line stays at zero.")
A78: ROOF HATCH
A79: Item | B79: RAW (before rounding) | C79: Qty | D79: Unit | E79: Unit $ | F79: Line Total
A80: Roof hatch | B80: =IF(N(Takeoff!B31)=0,"NA","") | C80: =IF(N(Takeoff!B31)=0,"NA",IFERROR(IF('Material Takeoff'!G158="","",'Material Takeoff'!G158),"")) | D80: ea | E80: =IF(OR(C80="NA",C80="",N(C80)=0),"",IFERROR(IF(VLOOKUP("Roof hatch",'Bid Products'!$A$4:$D$60,4,FALSE())="","",VLOOKUP("Roof hatch",'Bid Products'!$A$4:$D$60,4,FALSE())),"")) | F80: =IF(OR(C80="NA",C80="",E80=""),"",C80*E80)
A81: Safety ladder-up post | B81: =IF(N(Takeoff!B31)=0,"NA","") | C81: =IF(N(Takeoff!B31)=0,"NA",IFERROR(IF('Material Takeoff'!G159="","",'Material Takeoff'!G159),"")) | D81: ea | E81: =IF(OR(C81="NA",C81="",N(C81)=0),"",IFERROR(IF(VLOOKUP("Safety ladder-up post",'Bid Products'!$A$4:$D$60,4,FALSE())="","",VLOOKUP("Safety ladder-up post",'Bid Products'!$A$4:$D$60,4,FALSE())),"")) | F81: =IF(OR(C81="NA",C81="",E81=""),"",C81*E81)
A82: Backer rod | B82: =IF(N(Takeoff!B31)=0,"NA",IFERROR(IF('Material Takeoff'!F104="","",'Material Takeoff'!F104),"")) | C82: =IF(N(Takeoff!B31)=0,"NA",IFERROR(IF('Material Takeoff'!G104="","",'Material Takeoff'!G104),"")) | D82: bag | E82: =IF(OR(C82="NA",C82="",N(C82)=0),"",IFERROR(IF(VLOOKUP("Backer rod",'Bid Products'!$A$4:$D$60,4,FALSE())="","",VLOOKUP("Backer rod",'Bid Products'!$A$4:$D$60,4,FALSE())),"")) | F82: =IF(OR(C82="NA",C82="",E82=""),"",C82*E82)
A83: =IF(N(Takeoff!B31)=0,"NA — no roof hatch, so no backer rod.",IF(N('Material Takeoff'!D104)=0,"rule not set yet",IF(RIGHT('Material Takeoff'!E104,1)=".",'Material Takeoff'!E104,'Material Takeoff'!E104&".")&" "&TEXT(N('Material Takeoff'!B104),"#,##0.##")&" ÷ "&TEXT(N('Material Takeoff'!D104),"#,##0.##")&" = "&TEXT(N('Material Takeoff'!G104),"#,##0")&" bag"))
A84: Railing / guardrail set | B84: =IF(N(Takeoff!B31)=0,"NA","") | C84: =IF(N(Takeoff!B31)=0,"NA",IFERROR(IF('Material Takeoff'!G160="","",'Material Takeoff'!G160),"")) | D84: ea | E84: =IF(OR(C84="NA",C84="",N(C84)=0),"",IFERROR(IF(VLOOKUP("Railing / guardrail set",'Bid Products'!$A$4:$D$60,4,FALSE())="","",VLOOKUP("Railing / guardrail set",'Bid Products'!$A$4:$D$60,4,FALSE())),"")) | F84: =IF(OR(C84="NA",C84="",E84=""),"",C84*E84)
A85: Walkpad | B85: =IF(N('Material Takeoff'!B151)=0,"NA",IFERROR(IF('Material Takeoff'!F152="","",'Material Takeoff'!F152),"")) | C85: =IF(N('Material Takeoff'!B151)=0,"NA",IFERROR(IF('Material Takeoff'!G152="","",'Material Takeoff'!G152),"")) | D85: roll | E85: =IF(OR(C85="NA",C85="",N(C85)=0),"",IFERROR(IF(VLOOKUP("Walkpad",'Bid Products'!$A$4:$D$60,4,FALSE())="","",VLOOKUP("Walkpad",'Bid Products'!$A$4:$D$60,4,FALSE())),"")) | F85: =IF(OR(C85="NA",C85="",E85=""),"",C85*E85)
A86: ="Plan LF plus 10 ft for every roof hatch — both reasons in one number, so it is only counted once. "&TEXT(N('Material Takeoff'!B147),"#,##0")&" ft from the plan + "&TEXT(N('Material Takeoff'!B148),"0")&" hatch x "&TEXT(N('Material Takeoff'!B149),"0")&" ft = "&TEXT(N('Material Takeoff'!B151),"#,##0")&" ft. A roll is "&TEXT(N('Material Takeoff'!B150),"0")&" ft: "&TEXT(N('Material Takeoff'!B151),"#,##0")&" ÷ "&TEXT(N('Material Takeoff'!B150),"0")&" = "&TEXT(N('Material Takeoff'!F152),"0.00")&" → "&TEXT(N('Material Takeoff'!G152),"0.00")&" rolls. A partial buys a quarter, a half or the whole roll — never a full roll for a few feet."
A88: METAL
A89: Item | B89: RAW (before rounding) | C89: Qty | D89: Unit | E89: Unit $ | F89: Line Total
A90: Coping metal | B90: =IF(AND(N(Takeoff!B62)=0,N(Takeoff!B111)=0),"NA",IFERROR(IF('Material Takeoff'!B119="","",'Material Takeoff'!B119),"")) | C90: =IF(AND(N(Takeoff!B62)=0,N(Takeoff!B111)=0),"NA",IFERROR(IF('Material Takeoff'!G119="","",'Material Takeoff'!G119),"")) | D90: sheet / LF | E90: =IF(OR(C90="NA",C90="",N(C90)=0),"",IFERROR(IF(VLOOKUP("Coping metal",'Bid Products'!$A$4:$D$60,4,FALSE())="","",VLOOKUP("Coping metal",'Bid Products'!$A$4:$D$60,4,FALSE())),"")) | F90: =IF(OR(C90="NA",C90="",E90=""),"",C90*E90)
A91: =IF(AND(N(Takeoff!B62)=0,N(Takeoff!B111)=0),"NA — every wall facet on this roof is terminated in E2 GRAVEL STOP. The check on the Takeoff (F · row 1) reads OK, which means no facet is left without a termination. So there is no coping cap on this job.",IF(N(MAX(Takeoff!C54:C64))=0,"no stretch-out set yet","Each run rounds up to its own sheet, then they add up. 48 ÷ "&TEXT(N(MAX(Takeoff!C54:C64)),"0.##")&" in. stretch-out = "&TEXT(ROUNDDOWN(48/MAX(Takeoff!C54:C64),0),"0")&" strips x 10 ft = "&TEXT((ROUNDDOWN(48/MAX(Takeoff!C54:C64),0)*10),"0")&" ft a sheet. "&TEXT(N(Takeoff!B62),"#,##0")&" LF → "&TEXT(N('Material Takeoff'!G119),"0")&" sheets"))
A92: Coping cleat | B92: =IF(AND(N(Takeoff!B62)=0,N(Takeoff!B111)=0),"NA",IFERROR(IF('Material Takeoff'!B124="","",'Material Takeoff'!B124),"")) | C92: =IF(AND(N(Takeoff!B62)=0,N(Takeoff!B111)=0),"NA",IFERROR(IF('Material Takeoff'!G124="","",'Material Takeoff'!G124),"")) | D92: sheet | E92: =IF(OR(C92="NA",C92="",N(C92)=0),"",IFERROR(IF(VLOOKUP("Coping cleat",'Bid Products'!$A$4:$D$60,4,FALSE())="","",VLOOKUP("Coping cleat",'Bid Products'!$A$4:$D$60,4,FALSE())),"")) | F92: =IF(OR(C92="NA",C92="",E92=""),"",C92*E92)
A93: =IF(AND(N(Takeoff!B62)=0,N(Takeoff!B111)=0),"NA — every wall facet on this roof is terminated in E2 GRAVEL STOP. The check on the Takeoff (F · row 1) reads OK, which means no facet is left without a termination. So there is no coping cleat on this job.",IF(N(Takeoff!E102)=0,"no stretch-out set yet","Every coping cap gets a cleat, and it runs the coping's own stretch-out. 48 ÷ "&TEXT(N(Takeoff!E102),"0.##")&" in. stretch-out = "&TEXT(ROUNDDOWN(48/Takeoff!E102,0),"0")&" strips x 10 ft = "&TEXT(Takeoff!F102,"0")&" ft a sheet. "&TEXT(N(Takeoff!B102),"#,##0")&" LF → "&TEXT(N('Material Takeoff'!G124),"0")&" sheets"))
A94: Gravel stop metal | B94: =IFERROR(IF(N(MAX(Takeoff!C68:C80))=0,"",SUM(Takeoff!F68:F80)),"") | C94: =IFERROR(IF('Material Takeoff'!G120="","",'Material Takeoff'!G120),"") | D94: sheet / LF | E94: =IF(OR(C94="NA",C94="",N(C94)=0),"",IFERROR(IF(VLOOKUP("Gravel stop metal",'Bid Products'!$A$4:$D$60,4,FALSE())="","",VLOOKUP("Gravel stop metal",'Bid Products'!$A$4:$D$60,4,FALSE())),"")) | F94: =IF(OR(C94="NA",C94="",E94=""),"",C94*E94)
A95: =IF(N(MAX(Takeoff!C68:C78))=0,"no stretch-out set yet","Each run rounds up to its own sheet, then they add up. 48 ÷ "&TEXT(N(MAX(Takeoff!C68:C78)),"0.##")&" in. stretch-out = "&TEXT(ROUNDDOWN(48/MAX(Takeoff!C68:C78),0),"0")&" strips x 10 ft = "&TEXT((ROUNDDOWN(48/MAX(Takeoff!C68:C78),0)*10),"0")&" ft a sheet. "&TEXT(N(Takeoff!B76),"#,##0")&" LF → "&TEXT(N('Material Takeoff'!G120),"0")&" sheets")
A96: Gravel stop cleat | B96: =IFERROR(IF(OR(Takeoff!B103="",N(Takeoff!F103)=0),"",Takeoff!B103/Takeoff!F103),"") | C96: =IFERROR(IF('Material Takeoff'!G125="","",'Material Takeoff'!G125),"") | D96: sheet | E96: =IF(OR(C96="NA",C96="",N(C96)=0),"",IFERROR(IF(VLOOKUP("Gravel stop cleat",'Bid Products'!$A$4:$D$60,4,FALSE())="","",VLOOKUP("Gravel stop cleat",'Bid Products'!$A$4:$D$60,4,FALSE())),"")) | F96: =IF(OR(C96="NA",C96="",E96=""),"",C96*E96)
A97: =IF(N(Takeoff!E103)=0,"no stretch-out set yet","Face is over 3½ in., so this piece gets a cleat. 48 ÷ "&TEXT(N(Takeoff!E103),"0.##")&" in. stretch-out = "&TEXT(ROUNDDOWN(48/Takeoff!E103,0),"0")&" strips x 10 ft = "&TEXT(Takeoff!F103,"0")&" ft a sheet. "&TEXT(N(Takeoff!B103),"#,##0")&" LF → "&TEXT(N('Material Takeoff'!G125),"0")&" sheets")
A98: Counter flashing metal | B98: =IF(AND(N(Takeoff!B90)=0,N(Takeoff!B111)=0),"NA",IFERROR(IF('Material Takeoff'!B121="","",'Material Takeoff'!B121),"")) | C98: =IF(AND(N(Takeoff!B90)=0,N(Takeoff!B111)=0),"NA",IFERROR(IF('Material Takeoff'!G121="","",'Material Takeoff'!G121),"")) | D98: sheet / LF | E98: =IF(OR(C98="NA",C98="",N(C98)=0),"",IFERROR(IF(VLOOKUP("Counter flashing metal",'Bid Products'!$A$4:$D$60,4,FALSE())="","",VLOOKUP("Counter flashing metal",'Bid Products'!$A$4:$D$60,4,FALSE())),"")) | F98: =IF(OR(C98="NA",C98="",E98=""),"",C98*E98)
A99: =IF(AND(N(Takeoff!B90)=0,N(Takeoff!B111)=0),"NA — every wall facet on this roof is terminated in E2 GRAVEL STOP. The check on the Takeoff (F · row 1) reads OK, which means no facet is left without a termination. So there is no counter flashing on this job.",IF(N(MAX(Takeoff!C82:C94))=0,"no stretch-out set yet","Each run rounds up to its own sheet, then they add up. 48 ÷ "&TEXT(N(MAX(Takeoff!C82:C94)),"0.##")&" in. stretch-out = "&TEXT(ROUNDDOWN(48/MAX(Takeoff!C82:C94),0),"0")&" strips x 10 ft = "&TEXT((ROUNDDOWN(48/MAX(Takeoff!C82:C94),0)*10),"0")&" ft a sheet. "&TEXT(N(Takeoff!B90),"#,##0")&" LF → "&TEXT(N('Material Takeoff'!G121),"0")&" sheets"))
A100: Gutter metal | B100: =IF(N(Takeoff!B95)=0,"NA",IFERROR(IF(OR(Takeoff!B95="",N(Takeoff!E95)=0),"",Takeoff!B95/Takeoff!E95),"")) | C100: =IF(N(Takeoff!B95)=0,"NA",IFERROR(IF('Material Takeoff'!G123="","",'Material Takeoff'!G123),"")) | D100: sheet / LF | E100: =IF(OR(C100="NA",C100="",N(C100)=0),"",IFERROR(IF(VLOOKUP("Gutter metal",'Bid Products'!$A$4:$D$60,4,FALSE())="","",VLOOKUP("Gutter metal",'Bid Products'!$A$4:$D$60,4,FALSE())),"")) | F100: =IF(OR(C100="NA",C100="",E100=""),"",C100*E100)
A101: =IF(N(Takeoff!B95)=0,"NA — no gutters on this job. A gutter exists only where it is tagged on the takeoff.",IF(N(Takeoff!C95)=0,"no stretch-out set yet","48 ÷ "&TEXT(N(Takeoff!C95),"0.##")&" in. stretch-out = "&TEXT(ROUNDDOWN(48/Takeoff!C95,0),"0")&" strips x 10 ft = "&TEXT(N(Takeoff!E95),"0")&" ft a sheet. "&TEXT(N(Takeoff!B95),"#,##0")&" LF ÷ "&TEXT(N(Takeoff!E95),"0")&" = "&TEXT(N(Takeoff!B95)/N(Takeoff!E95),"0.00")&" → "&TEXT(N('Material Takeoff'!G123),"0")&" sheets"))
A102: Downspout metal | B102: =IFERROR(IF(OR(Takeoff!B94="",N(Takeoff!E94)=0),"",Takeoff!B94/Takeoff!E94),"") | C102: =IFERROR(IF('Material Takeoff'!G122="","",'Material Takeoff'!G122),"") | D102: sheet / LF | E102: =IF(OR(C102="NA",C102="",N(C102)=0),"",IFERROR(IF(VLOOKUP("Downspout metal",'Bid Products'!$A$4:$D$60,4,FALSE())="","",VLOOKUP("Downspout metal",'Bid Products'!$A$4:$D$60,4,FALSE())),"")) | F102: =IF(OR(C102="NA",C102="",E102=""),"",C102*E102)
A103: =IF(N(Takeoff!C94)=0,"no stretch-out set yet","48 ÷ "&TEXT(N(Takeoff!C94),"0.##")&" in. stretch-out = "&TEXT(ROUNDDOWN(48/Takeoff!C94,0),"0")&" strips x 10 ft = "&TEXT(N(Takeoff!E94),"0")&" ft a sheet. "&TEXT(N(Takeoff!B94),"#,##0")&" LF ÷ "&TEXT(N(Takeoff!E94),"0")&" = "&TEXT(N(Takeoff!B94)/N(Takeoff!E94),"0.00")&" → "&TEXT(N('Material Takeoff'!G122),"0")&" sheets")
A104: Scuppers | C104: =IFERROR(IF('Material Takeoff'!B130="","",'Material Takeoff'!B130),"") | D104: ea | E104: =IF(OR(C104="NA",C104="",N(C104)=0),"",IFERROR(IF(VLOOKUP("Scuppers",'Bid Products'!$A$4:$D$60,4,FALSE())="","",VLOOKUP("Scuppers",'Bid Products'!$A$4:$D$60,4,FALSE())),"")) | F104: =IF(OR(C104="NA",C104="",E104=""),"",C104*E104)
A105: ="Price per each is a FINAL number — material, labor, overhead and profit are already in it. Do NOT mark it up. It sits here and not on the Labor page so it stays tied to the takeoff count and cannot get missed."
A106: Collector heads | C106: =IFERROR(IF('Material Takeoff'!B131="","",'Material Takeoff'!B131),"") | D106: ea | E106: =IF(OR(C106="NA",C106="",N(C106)=0),"",IFERROR(IF(VLOOKUP("Collector heads",'Bid Products'!$A$4:$D$60,4,FALSE())="","",VLOOKUP("Collector heads",'Bid Products'!$A$4:$D$60,4,FALSE())),"")) | F106: =IF(OR(C106="NA",C106="",E106=""),"",C106*E106)
...

Sheet TPO Labor
A1: TPO LABOR — MECHANICALLY ATTACHED TPO · TEAR-OFF
A2: One row per trade. Read across: what it costs in labor, what it costs per square, and what travel adds. This page totals TPO ONLY — metal is on its own page.
A4: RATES — the only cells you set are green
A5: Wage per man / day | B5: 270 | D5: OUT OF TOWN? | F5: N
A6: Overhead margin | B6: 0.5 | D6: =IF($F$5="Y","Per diem $ / man / day","Per diem $ / man / day — not asked, this job is local") | F6: 60
A7: COST PER MAN / DAY | B7: =IFERROR(IF(N(B6)=0,"",N(B5)/N(B6)),"") | D7: =IF($F$5="Y","Hotel $ / room / night","Hotel $ / room / night — not asked, this job is local") | F7: 150
D8: =IF($F$5="Y","Travel markup","Travel markup — not asked, this job is local") | F8: 0.3
A9: ="Overhead is a margin, so it DIVIDES: "&TEXT(N(B5),"$#,##0")&" ÷ "&TEXT(N(B6),"0%")&" = "&TEXT(N(B7),"$#,##0")&" a man a day. Travel is OFF until OUT OF TOWN says Y — it is "&IF($F$5="Y","Y, travel is ON.","N, travel is OFF.")
A10: TRADE | B10: MEN | C10: CREW $/DAY | D10: QTY | E10: UNIT | F10: PER DAY | G10: DAYS | H10: LABOR $ | I10: PRICE PER SQUARE | J10: PER DIEM | K10: HOTEL | L10: TRAVEL MKUP | M10: TRADE TOTAL
A11: Field | C11: =IFERROR(N(B11)*N('TPO Labor'!$B$7),"") | D11: =IFERROR('Material Takeoff'!G6,"") | E11: sq | G11: =IFERROR(IF(N(F11)=0,"",N(D11)/N(F11)),"") | H11: =IFERROR(IF(OR(N(G11)=0,N(C11)=0),"",N(G11)*N(C11)),"") | I11: =IFERROR(IF(N(D11)=0,"",N(H11)/N(D11)),"") | J11: =IFERROR(IF(OR(N(B11)=0,N(G11)=0),"",N(B11)*N(G11)*N('TPO Labor'!$F$6))*IF('TPO Labor'!$F$5="Y",1,0),"") | K11: =IFERROR(IF(OR(N(B11)=0,N(G11)=0),"",ROUNDUP(N(B11)/2,0)*N(G11)*N('TPO Labor'!$F$7))*IF('TPO Labor'!$F$5="Y",1,0),"") | L11: =IFERROR((N(J11)+N(K11))*N('TPO Labor'!$F$8),"") | M11: =IFERROR(N(H11)+N(J11)+N(K11)+N(L11),"")
A12: Field details | C12: =IFERROR(N(B12)*N('TPO Labor'!$B$7),"") | D12: =IFERROR('Material Takeoff'!G6,"") | E12: sq | G12: =IFERROR(IF(N(F12)=0,"",N(D12)/N(F12)),"") | H12: =IFERROR(IF(OR(N(G12)=0,N(C12)=0),"",N(G12)*N(C12)),"") | I12: =IFERROR(IF(N(D12)=0,"",N(H12)/N(D12)),"") | J12: =IFERROR(IF(OR(N(B12)=0,N(G12)=0),"",N(B12)*N(G12)*N('TPO Labor'!$F$6))*IF('TPO Labor'!$F$5="Y",1,0),"") | K12: =IFERROR(IF(OR(N(B12)=0,N(G12)=0),"",ROUNDUP(N(B12)/2,0)*N(G12)*N('TPO Labor'!$F$7))*IF('TPO Labor'!$F$5="Y",1,0),"") | L12: =IFERROR((N(J12)+N(K12))*N('TPO Labor'!$F$8),"") | M12: =IFERROR(N(H12)+N(J12)+N(K12)+N(L12),"")
A13: Walls | C13: =IFERROR(N(B13)*N('TPO Labor'!$B$7),"") | D13: =IFERROR('Material Takeoff'!G8,"") | E13: sq | G13: =IFERROR(IF(N(F13)=0,"",N(D13)/N(F13)),"") | H13: =IFERROR(IF(OR(N(G13)=0,N(C13)=0),"",N(G13)*N(C13)),"") | I13: =IFERROR(IF(N(D13)=0,"",N(H13)/N(D13)),"") | J13: =IFERROR(IF(OR(N(B13)=0,N(G13)=0),"",N(B13)*N(G13)*N('TPO Labor'!$F$6))*IF('TPO Labor'!$F$5="Y",1,0),"") | K13: =IFERROR(IF(OR(N(B13)=0,N(G13)=0),"",ROUNDUP(N(B13)/2,0)*N(G13)*N('TPO Labor'!$F$7))*IF('TPO Labor'!$F$5="Y",1,0),"") | L13: =IFERROR((N(J13)+N(K13))*N('TPO Labor'!$F$8),"") | M13: =IFERROR(N(H13)+N(J13)+N(K13)+N(L13),"")
A14: Wall details | C14: =IFERROR(N(B14)*N('TPO Labor'!$B$7),"") | D14: =IFERROR('Material Takeoff'!G8,"") | E14: sq | G14: =IFERROR(IF(N(F14)=0,"",N(D14)/N(F14)),"") | H14: =IFERROR(IF(OR(N(G14)=0,N(C14)=0),"",N(G14)*N(C14)),"") | I14: =IFERROR(IF(N(D14)=0,"",N(H14)/N(D14)),"") | J14: =IFERROR(IF(OR(N(B14)=0,N(G14)=0),"",N(B14)*N(G14)*N('TPO Labor'!$F$6))*IF('TPO Labor'!$F$5="Y",1,0),"") | K14: =IFERROR(IF(OR(N(B14)=0,N(G14)=0),"",ROUNDUP(N(B14)/2,0)*N(G14)*N('TPO Labor'!$F$7))*IF('TPO Labor'!$F$5="Y",1,0),"") | L14: =IFERROR((N(J14)+N(K14))*N('TPO Labor'!$F$8),"") | M14: =IFERROR(N(H14)+N(J14)+N(K14)+N(L14),"")
A15: Curb flashing | D15: =IFERROR('Material Takeoff'!B137,"") | E15: LF | H15: =IFERROR(IF(OR(N(D15)=0,N(I15)=0),"",N(D15)*N(I15)),"") | M15: =IFERROR(N(H15),"")
A16: Pitch pans | D16: =IFERROR('Material Takeoff'!B133,"") | E16: ea | H16: =IFERROR(IF(OR(N(D16)=0,N(I16)=0),"",N(D16)*N(I16)),"") | M16: =IFERROR(N(H16),"")
A17: Pipe boots | D17: =IFERROR('Material Takeoff'!B134,"") | E17: ea | H17: =IFERROR(IF(OR(N(D17)=0,N(I17)=0),"",N(D17)*N(I17)),"") | M17: =IFERROR(N(H17),"")
A18: TPO LABOR — PAGE TOTAL | H18: =IFERROR(SUM(H11:H17),"") | I18: =IFERROR(IF((N('Material Takeoff'!G6)+N('Material Takeoff'!G8))=0,"",N(H18)/(N('Material Takeoff'!G6)+N('Material Takeoff'!G8))),"") | J18: =IFERROR(SUM(J11:J17),"") | K18: =IFERROR(SUM(K11:K17),"") | L18: =IFERROR(SUM(L11:L17),"") | M18: =IFERROR(SUM(M11:M17),"")
A19: Yellow = labor. Green = per diem. Blue = hotel. Orange = travel markup. Purple = what that sub gets paid, all in. Every colour adds straight down its own column.

Sheet Metal Labor
A1: METAL LABOR — MECHANICALLY ATTACHED TPO · TEAR-OFF
A2: One row per trade. Same columns as the TPO page. Rates are set on the TPO Labor page. This page totals METAL ONLY.
A4: TRADE | B4: MEN | C4: CREW $/DAY | D4: QTY | E4: UNIT | F4: PER DAY | G4: DAYS | H4: LABOR $ | I4: $ PER UNIT | J4: PER DIEM | K4: HOTEL | L4: TRAVEL MKUP | M4: TRADE TOTAL
A5: Gravel stop | C5: =IFERROR(N(B5)*N('TPO Labor'!$B$7),"") | D5: =IFERROR('Material Takeoff'!B120,"") | E5: LF | G5: =IFERROR(IF(N(F5)=0,"",N(D5)/N(F5)),"") | H5: =IFERROR(IF(OR(N(G5)=0,N(C5)=0),"",N(G5)*N(C5)),"") | I5: =IFERROR(IF(N(D5)=0,"",N(H5)/N(D5)),"") | J5: =IFERROR(IF(OR(N(B5)=0,N(G5)=0),"",N(B5)*N(G5)*N('TPO Labor'!$F$6))*IF('TPO Labor'!$F$5="Y",1,0),"") | K5: =IFERROR(IF(OR(N(B5)=0,N(G5)=0),"",ROUNDUP(N(B5)/2,0)*N(G5)*N('TPO Labor'!$F$7))*IF('TPO Labor'!$F$5="Y",1,0),"") | L5: =IFERROR((N(J5)+N(K5))*N('TPO Labor'!$F$8),"") | M5: =IFERROR(N(H5)+N(J5)+N(K5)+N(L5),"")
A6: Gravel stop cleat | C6: =IFERROR(N(B6)*N('TPO Labor'!$B$7),"") | D6: =IFERROR(Takeoff!B103,"") | E6: LF | G6: =IFERROR(IF(N(F6)=0,"",N(D6)/N(F6)),"") | H6: =IFERROR(IF(OR(N(G6)=0,N(C6)=0),"",N(G6)*N(C6)),"") | I6: =IFERROR(IF(N(D6)=0,"",N(H6)/N(D6)),"") | J6: =IFERROR(IF(OR(N(B6)=0,N(G6)=0),"",N(B6)*N(G6)*N('TPO Labor'!$F$6))*IF('TPO Labor'!$F$5="Y",1,0),"") | K6: =IFERROR(IF(OR(N(B6)=0,N(G6)=0),"",ROUNDUP(N(B6)/2,0)*N(G6)*N('TPO Labor'!$F$7))*IF('TPO Labor'!$F$5="Y",1,0),"") | L6: =IFERROR((N(J6)+N(K6))*N('TPO Labor'!$F$8),"") | M6: =IFERROR(N(H6)+N(J6)+N(K6)+N(L6),"")
A7: Downspouts | C7: =IFERROR(N(B7)*N('TPO Labor'!$B$7),"") | D7: =IFERROR('Material Takeoff'!B122,"") | E7: LF | G7: =IFERROR(IF(N(F7)=0,"",N(D7)/N(F7)),"") | H7: =IFERROR(IF(OR(N(G7)=0,N(C7)=0),"",N(G7)*N(C7)),"") | I7: =IFERROR(IF(N(D7)=0,"",N(H7)/N(D7)),"") | J7: =IFERROR(IF(OR(N(B7)=0,N(G7)=0),"",N(B7)*N(G7)*N('TPO Labor'!$F$6))*IF('TPO Labor'!$F$5="Y",1,0),"") | K7: =IFERROR(IF(OR(N(B7)=0,N(G7)=0),"",ROUNDUP(N(B7)/2,0)*N(G7)*N('TPO Labor'!$F$7))*IF('TPO Labor'!$F$5="Y",1,0),"") | L7: =IFERROR((N(J7)+N(K7))*N('TPO Labor'!$F$8),"") | M7: =IFERROR(N(H7)+N(J7)+N(K7)+N(L7),"")
A8: 2 x 8 nailer | C8: =IFERROR(N(B8)*N('TPO Labor'!$B$7),"") | D8: =IFERROR('Material Takeoff'!G166,"") | E8: LF | G8: =IFERROR(IF(N(F8)=0,"",N(D8)/N(F8)),"") | H8: =IFERROR(IF(OR(N(G8)=0,N(C8)=0),"",N(G8)*N(C8)),"") | I8: =IFERROR(IF(N(D8)=0,"",N(H8)/N(D8)),"") | J8: =IFERROR(IF(OR(N(B8)=0,N(G8)=0),"",N(B8)*N(G8)*N('TPO Labor'!$F$6))*IF('TPO Labor'!$F$5="Y",1,0),"") | K8: =IFERROR(IF(OR(N(B8)=0,N(G8)=0),"",ROUNDUP(N(B8)/2,0)*N(G8)*N('TPO Labor'!$F$7))*IF('TPO Labor'!$F$5="Y",1,0),"") | L8: =IFERROR((N(J8)+N(K8))*N('TPO Labor'!$F$8),"") | M8: =IFERROR(N(H8)+N(J8)+N(K8)+N(L8),"")
A9: Shop fabrication — flat metal | D9: =IFERROR(Takeoff!G106,"") | E9: sheet | H9: =IFERROR(IF(OR(N(D9)=0,N(I9)=0),"",N(D9)*N(I9)),"") | M9: =IFERROR(N(H9),"")
A10: 7/16" OSB install | D10: =IFERROR('Material Takeoff'!G167,"") | E10: sheet | H10: =IFERROR(IF(OR(N(D10)=0,N(I10)=0),"",N(D10)*N(I10)),"") | M10: =IFERROR(N(H10),"")
A11: METAL LABOR — PAGE TOTAL | H11: =IFERROR(SUM(H5:H10),"") | J11: =IFERROR(SUM(J5:J10),"") | K11: =IFERROR(SUM(K5:K10),"") | L11: =IFERROR(SUM(L5:L10),"") | M11: =IFERROR(SUM(M5:M10),"")
A12: Shop fabrication and OSB carry no per diem and no hotel — that work happens at the shop, not in Houston.

Sheet Totals
A1: TOTALS — MECHANICALLY ATTACHED TPO
A2: Materials. Labor. Travel. Everything else. That is the whole page.
A4: MATERIALS
A5: Materials w/ tax | B5: =IFERROR('Material Order'!F134,"") | C5: every material on the Material Order page, tax included
A6: Material markup % | C6: VARIABLE — set it on THIS job. Materials carry no markup until it is answered.
A7: Material markup | B7: =IFERROR((N('Material Order'!F134)-(N('Material Order'!F104)+N('Material Order'!F106))*(1+N('Material Order'!E133)))*N(B6),"") | C7: scuppers and collector heads are all-in — they do not get marked up
A9: LABOR
A10: TPO labor | B10: =IFERROR('TPO Labor'!H18,"") | C10: TPO Labor page, LABOR $ column total
A11: Metal labor | B11: =IFERROR('Metal Labor'!H11,"") | C11: Metal Labor page, LABOR $ column total
A13: TRAVEL — two crews, kept apart
A14: TPO crew — per diem | B14: =IFERROR('TPO Labor'!J18,"") | C14: green column, TPO Labor page
A15: TPO crew — hotels | B15: =IFERROR('TPO Labor'!K18,"") | C15: blue column, TPO Labor page
A16: TPO crew — travel markup | B16: =IFERROR('TPO Labor'!L18,"") | C16: orange column, TPO Labor page
A17: Metal crew — per diem | B17: =IFERROR('Metal Labor'!J11,"") | C17: green column, Metal Labor page
A18: Metal crew — hotels | B18: =IFERROR('Metal Labor'!K11,"") | C18: blue column, Metal Labor page
A19: Metal crew — travel markup | B19: =IFERROR('Metal Labor'!L11,"") | C19: orange column, Metal Labor page
A20: ="All six read zero unless OUT OF TOWN on the TPO Labor page is set to Y. It is "&IF('TPO Labor'!$B$8="Y","Y — travel is ON.","N — travel is OFF.")
A22: BEFORE THIS GOES OUT
A23: Warranty / NDL
A24: Special insurance
A25: Tool purchase / rental
A26: Bonds (P&P / performance)
A27: Skytrack rental
A28: Dumpsters | B28: =IFERROR(ROUNDUP(N(B33)/10,0)*700,"") | C28: $700 a dumpster, one load every 10 squares
A29: Misc markup % | C29: VARIABLE — set it on THIS job. Applies to insurance, tools, bonds, Skytrack, dumpsters. Nothing marks up until it is answered.
A30: Misc markup | B30: =IFERROR((N(B24)+N(B25)+N(B26)+N(B27)+N(B28))*N(B29),"")
A32: TOTAL BID | B32: =IFERROR(N(B5)+N(B7)+N(B10)+N(B11)+N(B14)+N(B15)+N(B16)+N(B17)+N(B18)+N(B19)+N(B23)+N(B24)+N(B25)+N(B26)+N(B27)+N(B28)+N(B30),"")
A33: Total squares | B33: =IFERROR('Material Takeoff'!G9,"")
A34: PRICE PER SQUARE | B34: =IFERROR(IF(N(B33)=0,"",N(B32)/N(B33)),"")
A35: Every line above is one number from one place. Nothing on this page is calculated twice.

Sheet Bid Products
A1: BID PRODUCTS — what this job actually buys
A2: One row per Material Order line. Every product below is the exact line off Blake Babcock's sheet (Specialized Building Materials, 8/25/26) — item number, pack size, price. Anything with no item number is not on that sheet.
A3: Material Order line | B3: Product (from the applied manufacturer price sheet) | C3: Unit | D3: PRICE | E3: Note | F3: How the price is figured
A4: TPO field membrane 10' | B4: 31012 GAF TPO .060 Wht 10'X100' · 10 SQ/ROLL | C4: roll | D4: 710 | F4: $0.710/sf x 1,000 sf (10 ft x 100 ft roll) = $710.00 a roll
A5: TPO field membrane 5' | B5: 31014 GAF TPO .060 Wht 5'X100' · 5 SQ/ROLL | C5: roll | D5: 355 | F5: $0.710/sf x 500 sf (5 ft x 100 ft roll) = $355.00 a roll
A6: Polyiso — field of the roof | B6: 12004 Insulation ISO 1.6" (LTTR 9.4) 4x8 · 51 BDFT/EA | C6: board | D6: 21.76 | E6: $68.00/sq on the sheet | F6: 4x8 = 32 sf. 32 sf x 1.6 in = 51.2 board-feet. 51.2 x $0.425/bdft = $21.76 a board
A7: Crickets — Scuppers / Drains · Q board | B7: 11000 ISO Taper Panel Q (0.5"-2.5") 4x4 · 24 BDFT/EA | C7: board | D7: 14.28 | E7: $89.25/sq on the sheet | F7: Q panel is 0.5-2.5 in, so 1.5 in average. 4x4 = 16 sf. 16 x 1.5 = 24 board-feet. 24 x $0.595/bdft = $14.28 a board
A8: Crickets — Units · Q board | B8: 11000 ISO Taper Panel Q (0.5"-2.5") 4x4 · 24 BDFT/EA | C8: board | D8: 14.28 | E8: $89.25/sq on the sheet | F8: Q panel is 0.5-2.5 in, so 1.5 in average. 4x4 = 16 sf. 16 x 1.5 = 24 board-feet. 24 x $0.595/bdft = $14.28 a board
A9: ISO plates | B9: 20000 GAF Drill-Tec Stnd Flat Steel Galv Insul Plate 3" (#4181B) · 500/EA | C9: box | D9: 118.96 | F9: $118.96 a box of 500 = $0.238 a plate
A10: Seam plates | B10: 20003 GAF Drill-Tec 2-3/8" EGX-FM Steel Plate, Barbed · 1000/EA | C10: box | D10: 376.44 | E10: sheet says 2-3/8", not the 2-3/4" in the crosswalk | F10: $376.44 a box of 1,000 = $0.376 a plate
A11: Insulation fasteners #12 | B11: 20011 GAF Drill-Tec 5" #12 Fastener · #3 Phillips · 1000/EA | C11: box | D11: 270.32 | E11: IT IS on Blake's sheet. Claude's earlier "#12 HD" was invented — this is the real line. | F11: $270.32 a box of 1,000 = $0.270 a screw
A12: Seam fasteners #15 — 5" | B12: 20037 GAF Drill-Tec 5" #15 Washer Head Fastener · #3 Phillips · 500/EA | C12: box | D12: 192.69 | E12: PACK IS 500, not 1000. The sheet was built on 1000 — corrected. | F12: $192.69 a box of 500 = $0.385 a screw. PACK IS 500, not 1,000.
A13: Bonding adhesive | B13: 41022 GAF TPO #1121 Solvent Based Bonding Adhesive 5GL | C13: pail | D13: 149.5 | F13: $149.50 a 5-gallon pail
A14: Rollers | B14: shop supply | C14: ea | D14: 5 | E14: shop supply — not on Blake's sheet | F14: shop supply — $5.00 each
A15: Cages | B15: shop supply | C15: ea | D15: 5 | E15: shop supply — not on Blake's sheet | F15: shop supply — $5.00 each
A16: Sticks | B16: shop supply | C16: ea | D16: 5 | E16: shop supply — not on Blake's sheet | F16: shop supply — $5.00 each
A17: Unsupported flashing | B17: 41044 GAF TPO UN-55 Flexible Detail Memb. Wht 24"X50' · 50 LF/ROLL | C17: roll | D17: 435.5 | F17: $435.50 a roll. 24 in x 50 ft = 100 sf a roll = $4.36/sf
A18: TPO T-joints | B18: 41037 GAF TPO Flexible T-Joint Patch White 4"X4" · 100/EA | C18: box | D18: 99 | F18: $99.00 a box of 100 = $0.99 a patch
A19: TPO corners | B19: 41028 GAF TPO Flexible Fluted Outside Corner 8" Diameter · 20 EA/CTN | C19: ea | D19: 13.51 | E19: PICK ONE: 41045 Universal Corners 4"x4" is $12.69 — which corner do you run? | F19: $13.51 each. Comes 20 to a carton = $270.20 a carton, but it is bought by the piece.
A20: TPO molded pipe boots | B20: 41047 GAF TPO Vent Boots White 1"-6" · 6 EA/CTN | C20: ea | D20: 44.5 | F20: $44.50 each. 6 to a carton.
A21: Pitch pockets | B21: 41020 GAF Split Pourable Sealant Pocket White · 6 EA/CTN | C21: ea | D21: 59.5 | F21: $59.50 each. 6 to a carton.
A22: Pourable sealer | B22: 41015 GAF 1-Part Pourable Sealant White · 4 KT/CTN | C22: kit | D22: 85.8 | E22: was $85.50 — sheet says $85.80 | F22: $85.80 a kit. 4 kits to a carton.
A23: TPO cover tape | B23: 41023 GAF TPO Dbl Cover Tape Wht 6"X100' · 100 LF/ROLL | C23: roll | D23: 356.5 | E23: PICK ONE: 41033 Primerless Dbl $356.50 · 41024 Heatweld $388.50 · 41025 60M Flashing Strip 8"x100 $283.19 | F23: $356.50 a roll. 6 in x 100 ft = 100 LF a roll = $3.565/LF
A24: Primer | B24: IKO / Innovi TPO Tape Primer 3Gl (6/Ctn) | C24: can | D24: 164.75 | E24: LAW — 3-GALLON ONLY. Never the 1-gallon. Blake sells the IKO 3G; that is the line, every time. | F24: IKO / Innovi TPO Tape Primer 3 GALLON, 6 to a carton. $164.75 a jug.
A25: Brushes | B25: shop supply | C25: ea | D25: 5 | E25: shop supply — not on Blake's sheet | F25: shop supply — $5.00 each
A26: TPO cut-edge sealant | B26: 41027 GAF TPO Cut Edge Sealant Wht Pint · 12 EA/CTN | C26: tube | D26: 26.65 | F26: $26.65 a pint. 12 to a carton.
A27: TPO LVOC all-purpose | B27: 41017 GAF FlexSeal Caulk Grade (Red Label) · 20-10OZ/CTN | C27: can | D27: 14.59 | F27: $14.59 a tube. 20 tubes of 10 oz to a carton.
A28: Water block | B28: 41016 GAF Evrg Water Block Mastic 10.3oz · 25 EA/CTN | C28: tube | D28: 8.9 | F28: $8.90 a tube of 10.3 oz. 25 to a carton.
A29: TPO cleaner 5g | B29: Carlisle / QXO TPO seam cleaner 5-GALLON | C29: can | D29: 150 | E29: ESTIMATE — Adam gave $150 to stand in until the QXO invoice with the 5-gal cleaner is found. Not a quoted price. | F29: $150.00 a 5-gallon can
A30: Rags | B30: shop supply — box | C30: box | D30: 40 | E30: shop supply — not on Blake's sheet | F30: shop supply — $40.00 a box
A31: Hose clamps | B31: shop supply — box | C31: roll | D31: 100 | E31: shop supply — not on Blake's sheet | F31: shop supply — $100.00 a roll
A32: Roof hatch | B32: TRI-BUILT Roof Hatch Galvanized 36 x 30 · SKU TRIRHG3630 (TBG3036) · 1 pc | C32: ea | D32: 850 | E32: QXO invoice VG76853, 9/1/26, PO "FATE 20K ROOF HATCH" — 1 pc @ $850.00 + $70.13 tax = $920.13. Price, product and qty all checked AS 9/7/26.
A33: Safety ladder-up post | B33: NA | C33: ea | E33: NA — no safety ladder-up post on this job. No product, no price.
A34: Backer rod | B34: Backer rod — 20 ft bag | C34: bag | D34: 4 | E34: ESTIMATE — $4 a bag, from the earlier pricing notes ("~$4/20ft"). Never tied to an invoice. Not on Blake's sheet.
A35: Railing / guardrail set | B35: NA | C35: ea | E35: NA — no railing / guardrail set on this job. No product, no price.
A36: Walkpad | B36: 41048 GAF TPO Walkway Roll — Gray 34.25" x 50'5" · 50 LF/ROLL | C36: roll | D36: 665 | E36: Blake / SBM 8/25/26 sheet, page 31, item 41048 — $665.00 per 50 LF roll.
A37: Coping metal | B37: NA | C37: sheet | E37: NA — no coping metal on this job. No product, no price.
A38: Coping cleat | B38: NA | C38: sheet | E38: NA — no coping cleat on this job. No product, no price.
A39: Gravel stop metal | B39: 24g Kynar flat 4 x 10 | C39: sheet | D39: 80 | E39: QXO / metal supplier — not on Blake's sheet | F39: $80.00 a 4 ft x 10 ft sheet of 24g Kynar flat
A40: Gravel stop cleat | B40: MAJ G90 20GA GALVANIZED 4 x 10 — QXO MAJ20G90 | C40: sheet | D40: 58.5 | E40: QXO MAJ20G90 — not on Blake's sheet | F40: $58.50 a 4 ft x 10 ft sheet of 20g galv. QXO MAJ20G90, 7/22/26 invoice UZ87925.
A41: Counter flashing metal | B41: NA | C41: sheet | E41: NA — no counter flashing metal on this job. No product, no price.
A42: Gutter metal | B42: NA | C42: sheet | E42: NA — no gutter metal on this job. No product, no price.
A43: Downspout metal | B43: 24g Kynar flat 4 x 10 | C43: sheet | D43: 80 | E43: QXO / metal supplier — not on Blake's sheet | F43: $80.00 a 4 ft x 10 ft sheet of 24g Kynar flat
A44: Scuppers | C44: ea | D44: 200 | E44: FINAL all-in each (labor-loaded) — do NOT mark up. Adam 9/9: "Scuppers are $200 each. Leave it at that." | F44: $200.00 each, all-in — material, labor, overhead and profit already in it. Do NOT mark up.
A45: Collector heads | C45: ea | D45: 300 | E45: FINAL all-in each (labor-loaded) — do NOT mark up. Adam 9/9: "Collector heads $300 each. Leave it at that." | F45: $300.00 each, all-in — material, labor, overhead and profit already in it. Do NOT mark up.
A46: Crickets — Scuppers / Drains · 2″ fill board 4 ft x 4 ft | B46: 12010 Insulation ISO 2.0" (LTTR 11.4) 4x4 Fill · 32 BDFT/EA | C46: board | D46: 13.6 | F46: 4x4 = 16 sf. 16 sf x 2.0 in = 32 board-feet. 32 x $0.425/bdft = $13.60 a board
A47: Retro drains | B47: retro drain | C47: ea | D47: 300 | E47: ESTIMATE — not a quoted price. Confirm before this bid goes out. | F47: $300.00 each.
A48: 2 x 8 nailer | B48: 2 x 8 pressure-treated, 10 ft boards | C48: LF | D48: 1 | E48: lumber yard | F48: $10.00 a 10 ft board of 2x8 pressure-treated = $1.00 a linear foot
A49: 7/16" OSB — wall face | B49: 7/16" OSB 4 x 8 | C49: sheet | D49: 15 | E49: lumber yard | F49: $15.00 a 4 ft x 8 ft sheet of 7/16 in OSB
A50: Fasteners 3" #14 — blocking & sheathing | B50: 20018 GAF Drill-Tec 3" #14 Fastener · #3 Phillips · 1000/EA | C50: box | D50: 218.94 | F50: $218.94 a box of 1,000 = $0.219 a screw
A52: Seam fasteners #15 — 7" | B52: 20039 GAF Drill-Tec 7" #15 Washer Head Fastener · #3 Phillips · 500/EA | C52: box | D52: 369.73 | E52: for the crickets | F52: $369.73 a box of 500 = $0.739 a screw
A53: Seam fasteners #15 — 8" | B53: 20040 GAF Drill-Tec 8" #15 Washer Head Fastener · #3 Phillips · 500/EA | C53: box | D53: 449.6 | E53: for the crickets | F53: $449.60 a box of 500 = $0.899 a screw
A54: TPO wall membrane 5' | B54: 31014 GAF TPO .060 Wht 5'X100' · 5 SQ/ROLL | C54: roll | D54: 355 | E54: same roll as the field 5 ft — one product, two lines | F54: $0.710/sf x 500 sf (5 ft x 100 ft roll) = $355.00 a roll
A55: Material delivery | B55: delivery truck | C55: delivery | D55: 300 | E55: HOUSTON — $300 a delivery on this job. Normal rate is $200. One delivery every 50 squares, every bid. | F55: $300.00 a delivery (Houston rate; normal is $200)
A56: Metal delivery | B56: delivery truck | C56: delivery | D56: 200 | E56: $200 a delivery. Normally ONE covers the metal; this job is in Houston, so 3. | F56: $200.00 a delivery x 3 trips

Sheet Plan Reference
A1: PLAN REFERENCE — job:
A2: Where the wall numbers on the Takeoff page came from. Reference only — nothing here feeds a calculation. Read every job off its own plans.
A4: WALL SECTIONS — sheet numbers and the scale they are drawn at
A5: Condition | B5: T.O. parapet | C5: Parapet above deck | D5: Cap width | E5: Sections
A11: Check the printed cap dimensions against the scale before trusting any of it. A parapet FRAMING height is not the height above the roof deck.
A22: TERMINATION
A23: How every section terminates — write it here off this job's details.

Sheet Material Takeoff
A1: MATERIAL TAKEOFF — MECHANICALLY ATTACHED TPO
A2: PAGE TWO. Nothing is typed here except a FACTOR. Every driver reads live off the Takeoff page. Each line: DRIVER x/÷ FACTOR = RAW → QTY.
A4: 1 · SQUARES
A5: Item | B5: Driver | C5: Unit | E5: Where it comes from | G5: Squares
A6: Field squares | B6: =IFERROR(Takeoff!B20,"") | C6: sf | E6: Takeoff A · field squares | G6: =IFERROR(ROUNDUP(B6/100,0),"") | H6: sq
A8: Wall squares | B8: =IFERROR(Takeoff!H46,"") | C8: sf | E8: Takeoff C · total wall sq ft | G8: =IFERROR(ROUNDUP(B8/100,0),"") | H8: sq
A9: TOTAL SQUARES (field + walls) | E9: field squares + wall squares | G9: =IFERROR(N(G6)+N(G8),"") | H9: sq
A10: ="Field "&TEXT(G6,"0")&" sq · walls "&TEXT(G8,"0")&" sq · TOTAL "&TEXT(G9,"0")&" sq. Squares always round UP."
A12: 2 · INSULATION
A13: Item | B13: Driver | C13: Unit | D13: Factor | E13: What the factor means | F13: RAW | G13: Qty | H13: Pkg
A14: Polyiso — field of the roof | B14: =IFERROR(G6,"") | C14: sq | D14: 3 | E14: field squares x 3 | F14: =IFERROR(IF(OR(B14="",D14=""),"",B14*D14),"") | G14: =IFERROR(IF(F14="","",ROUNDUP(F14,0)),"") | H14: board
A17: "Squares x 3 = boards. Flat — no waste factor, because in the field those boards never seat like they did in the factory: an eighth of an inch between every one, cuts around everything, and a perimeter that is never snug to the wall. That IS the waste, and 3 covers it."
A19: 2b · Q BOARD — 2" tapered filler for the crickets
A20: "THE LAYOUT WINS. If the takeoff app drew this roof, its board count is the number — it lays the boards out one at a time and counts the leftovers. Only when there is no layout does the sheet fall back to cricket LF x 1.2 ÷ 4 ft board. 4″ and 2″ fill are two different boards off two different pallets and never get added together."
A21: Item | B21: Q board FROM THE LAYOUT | C21: Unit | D21: 2″ fill FROM THE LAYOUT | E21: Cricket LF (only if there is no layout) | F21: Fallback boards | G21: BOARDS USED | H21: Pkg | J21: Where the number came from
A22: Crickets — Units | C22: bd | F22: =IFERROR(IF(E22="","",ROUNDUP(E22*1.2/4,0)),"") | G22: =IFERROR(IF(B22<>"",B22,IF(F22<>"",F22,"")),"") | H22: board | I22: 52 units, one cricket per unit curb. 294.32 ft of leading edge on the layout. This scope can come out of the quote on its own. | J22: =IF(B22<>"","from the layout — the app counted the boards",IF(E22<>"","no layout, so LF x 1.2 ÷ 4","nothing to go on yet"))
A23: Crickets — Scuppers / Drains | C23: bd | F23: =IFERROR(IF(E23="","",ROUNDUP(E23*1.2/4,0)),"") | G23: =IFERROR(IF(B23<>"",B23,IF(F23<>"",F23,"")),"") | H23: board | I23: 7 crickets steering water to the scuppers and drains. 344.64 ft of leading edge on the layout. These have to be there. | J23: =IF(B23<>"","from the layout — the app counted the boards",IF(E23<>"","no layout, so LF x 1.2 ÷ 4","nothing to go on yet"))
A24: ="Units "&TEXT(N(G22),"0")&" Q board. Scuppers/Drains "&TEXT(N(G23),"0")&" Q board + "&TEXT(N(D23),"0")&" pieces of 2″ fill at 4 ft x 4 ft. "&IF(N(B22)+N(B23)>0,"Both taken off the drawn layout.","No layout — figured off cricket LF.")
A25: 3 · TPO MEMBRANE — 60-mil. 10 ft in the middle, 5 ft around the outside, 5 ft on the walls
A26: "A roll gives as many squares as it is feet wide — a 10 ft roll is 10 squares, a 5 ft roll is 5. Six inches of every roll is the selvage that gets lapped over, so a 5 ft roll loses 10% and a 10 ft roll only loses 5%. Cuts are on top of that."
A27: Item | B27: Driver | C27: Unit | D27: Cuts % | E27: Factor (1 + lap + cuts) | F27: RAW | G27: Qty | H27: Roll width (ft)
A28: Field membrane 10' (interior) | B28: =IFERROR(Takeoff!B129,"") | C28: sq | D28: 0.1 | E28: =IFERROR(IF(OR(D28="",H28=""),"",1+(0.5/H28)+D28),"") | F28: =IFERROR(IF(OR(B28="",E28="",H28=""),"",B28*E28/H28),"") | G28: =IFERROR(IF(F28="","",ROUNDUP(F28,0)),"") | H28: 10
A29: Field membrane 5' (perimeter) | B29: =IFERROR(Takeoff!B128,"") | C29: sq | D29: 0.1 | E29: =IFERROR(IF(OR(D29="",H29=""),"",1+(0.5/H29)+D29),"") | F29: =IFERROR(IF(OR(B29="",E29="",H29=""),"",B29*E29/H29),"") | G29: =IFERROR(IF(F29="","",ROUNDUP(F29,0)),"") | H29: 5
A30: Wall membrane 5' | B30: =IFERROR(G8,"") | C30: sq | D30: 0.15 | E30: =IFERROR(IF(OR(D30="",H30=""),"",1+(0.5/H30)+D30),"") | F30: =IFERROR(IF(OR(B30="",E30="",H30=""),"",B30*E30/H30),"") | G30: =IFERROR(IF(F30="","",ROUNDUP(F30,0)),"") | H30: 5
A31: ="Interior "&TEXT(N(B28),"0")&" sq x "&TEXT(E28,"0.00")&" ÷ 10 sq per roll = "&TEXT(N(G28),"0")&" rolls of 10 ft. Perimeter "&TEXT(N(B29),"0")&" sq x "&TEXT(E29,"0.00")&" ÷ 5 sq per roll = "&TEXT(N(G29),"0")&" rolls of 5 ft. Walls "&TEXT(N(B30),"0")&" sq x "&TEXT(E30,"0.00")&" ÷ 5 = "&TEXT(N(G30),"0")&" rolls."
A32: 4 · FASTENERS & SEAM PLATES
A33: "TWO SCREWS ON THIS ROOF, ONE LENGTH. The length falls out of the stack: insulation + the deck itself + a full inch through the bottom, rounded up to the next size. The gauges are a rule and do not move: the screw that holds the INSULATION down is a #12, the screw that holds a SEAM PLATE down is a #15."
A34: Item | B34: Value | C34: Unit | E34: How it is decided
A35: Fastener LENGTH (both screws) | B35: =IFERROR(ROUNDUP(N(Takeoff!B10)+N(Takeoff!B9)+IF(ISNUMBER(SEARCH("WOOD",UPPER(Takeoff!B8))),0.5,0)+1,0),"") | C35: in | E35: =IFERROR("insulation "&TEXT(N(Takeoff!B10),"0.0#")&"in + deck "&TEXT(N(Takeoff!B9)+IF(ISNUMBER(SEARCH("WOOD",UPPER(Takeoff!B8))),0.5,0),"0.0#")&"in + 1in through the bottom = "&TEXT(N(Takeoff!B10)+N(Takeoff!B9)+IF(ISNUMBER(SEARCH("WOOD",UPPER(Takeoff!B8))),0.5,0)+1,"0.0#")&"in, rounded up to "&TEXT(N(B35),"0")&"in. No cover board on this job.","")
A36: Insulation fastener GAUGE | B36: 12 | C36: gauge | E36: RULE. The screw that holds the insulation down is a #12. It does not change with the deck.
A37: Seam fastener GAUGE | B37: 15 | C37: gauge | E37: =IF(ISNUMBER(SEARCH("WOOD",UPPER(Takeoff!L38))),"RULE. Every seam plate takes a #15 — field, curbs, boots, pans. WOOD walls are the one exception: the wall and base-flashing plates take a 3in #14 into the wood.","RULE. Every seam plate takes a #15 — field, curbs, boots, pans, walls and base flashing. Walls are "&LOWER(Takeoff!L38)&", so nothing is screwed into the wall and there is no 3in #14 on this job.")
A38: ="Both screws are "&TEXT(N(B35),"0")&"in long. Insulation = #"&TEXT(N(B36),"0")&". Seam plates = #"&TEXT(N(B37),"0")&"."&IF(ISNUMBER(SEARCH("WOOD",UPPER(Takeoff!L38)))," Wood walls: the wall and base-flashing plates take a 3in #14 instead.","")
A40: Item | B40: Boards | C40: Unit | D40: Plates per board | E40: Plates per box | F40: RAW plates | G40: Boxes | H40: Pkg
A41: ISO plates | B41: =IFERROR(N(G14),"") | C41: board | D41: =IFERROR(Takeoff!B14,"") | E41: 500 | F41: =IFERROR(IF(OR(B41="",D41=""),"",B41*D41),"") | G41: =IFERROR(IF(OR(F41="",N(E41)=0),"",ROUNDUP(F41/E41,0)),"") | H41: box
A43: 4b · WALL FASTENING — 3" #14 + seam plate at 12" o.c., a seam every sheet width along the run
A44: "The run that gets fastened off is the WALL face. The cap is NOT in it — the membrane goes over the cap and terminates, it does not get a row up there. A seam lands every 5 ft along that run and the top one is not counted, because that is where it folds over."
A45: Rule | B45: Value | C45: Unit | E45: What it means
A46: Wall fastener row spacing (LAW — every 5 ft for wind uplift) | B46: 5 | C46: ft | E46: LAW, not a setting. A wall gets a row of fasteners every 5 ft up its height, for wind uplift. Run a 10 ft sheet on a wall and you still fasten fingers through its mid-point to keep the rows 5 ft apart. This does NOT follow the field sheet width.
A47: Cap is not part of the run | E47: the membrane runs over the cap and terminates — no fastener row up there
A48: Variance off the top | B48: 2 | C48: ft | E48: a row that lands inside this of the top is not worth putting in. 11 ft wall = 1 row, 12 ft wall = 2.
A49: Fastener spacing on center | B49: =IFERROR(Takeoff!B15,"") | C49: in | E49: from the SETUP block — the wind-uplift lever
A51: Wall facet | B51: Run of wall (ft) | C51: WALL run (no cap) | D51: Cap (ft) | E51: Rows of fasteners | F51: Fasteners | G51: Plates | H51: Pkg
A52: Facet 1 | B52: =IFERROR(IF(Takeoff!B38="","",Takeoff!B38),"") | C52: =IFERROR(IF(Takeoff!G38="","",Takeoff!G38-N(Takeoff!D38)),"") | D52: =IFERROR(IF(Takeoff!D38="","",Takeoff!D38),"") | E52: =IFERROR(IF(OR(C52="",B46=0),"",MAX(0,ROUNDDOWN((C52-N(B48))/B46,0))),"") | F52: =IFERROR(IF(OR(B52="",E52="",B49=0),"",E52*B52/(B49/12)),"") | H52: ea
A53: Facet 2 | B53: =IFERROR(IF(Takeoff!B39="","",Takeoff!B39),"") | C53: =IFERROR(IF(Takeoff!G39="","",Takeoff!G39-N(Takeoff!D39)),"") | D53: =IFERROR(IF(Takeoff!D39="","",Takeoff!D39),"") | E53: =IFERROR(IF(OR(C53="",B46=0),"",MAX(0,ROUNDDOWN((C53-N(B48))/B46,0))),"") | F53: =IFERROR(IF(OR(B53="",E53="",B49=0),"",E53*B53/(B49/12)),"") | H53: ea
A54: Facet 3 | B54: =IFERROR(IF(Takeoff!B40="","",Takeoff!B40),"") | C54: =IFERROR(IF(Takeoff!G40="","",Takeoff!G40-N(Takeoff!D40)),"") | D54: =IFERROR(IF(Takeoff!D40="","",Takeoff!D40),"") | E54: =IFERROR(IF(OR(C54="",B46=0),"",MAX(0,ROUNDDOWN((C54-N(B48))/B46,0))),"") | F54: =IFERROR(IF(OR(B54="",E54="",B49=0),"",E54*B54/(B49/12)),"") | H54: ea
A55: Facet 4 | B55: =IFERROR(IF(Takeoff!B41="","",Takeoff!B41),"") | C55: =IFERROR(IF(Takeoff!G41="","",Takeoff!G41-N(Takeoff!D41)),"") | D55: =IFERROR(IF(Takeoff!D41="","",Takeoff!D41),"") | E55: =IFERROR(IF(OR(C55="",B46=0),"",MAX(0,ROUNDDOWN((C55-N(B48))/B46,0))),"") | F55: =IFERROR(IF(OR(B55="",E55="",B49=0),"",E55*B55/(B49/12)),"") | H55: ea
A56: Facet 5 | B56: =IFERROR(IF(Takeoff!B42="","",Takeoff!B42),"") | C56: =IFERROR(IF(Takeoff!G42="","",Takeoff!G42-N(Takeoff!D42)),"") | D56: =IFERROR(IF(Takeoff!D42="","",Takeoff!D42),"") | E56: =IFERROR(IF(OR(C56="",B46=0),"",MAX(0,ROUNDDOWN((C56-N(B48))/B46,0))),"") | F56: =IFERROR(IF(OR(B56="",E56="",B49=0),"",E56*B56/(B49/12)),"") | H56: ea
A57: Facet 6 | B57: =IFERROR(IF(Takeoff!B43="","",Takeoff!B43),"") | C57: =IFERROR(IF(Takeoff!G43="","",Takeoff!G43-N(Takeoff!D43)),"") | D57: =IFERROR(IF(Takeoff!D43="","",Takeoff!D43),"") | E57: =IFERROR(IF(OR(C57="",B46=0),"",MAX(0,ROUNDDOWN((C57-N(B48))/B46,0))),"") | F57: =IFERROR(IF(OR(B57="",E57="",B49=0),"",E57*B57/(B49/12)),"") | H57: ea
A58: Facet 7 | B58: =IFERROR(IF(Takeoff!B44="","",Takeoff!B44),"") | C58: =IFERROR(IF(Takeoff!G44="","",Takeoff!G44-N(Takeoff!D44)),"") | D58: =IFERROR(IF(Takeoff!D44="","",Takeoff!D44),"") | E58: =IFERROR(IF(OR(C58="",B46=0),"",MAX(0,ROUNDDOWN((C58-N(B48))/B46,0))),"") | F58: =IFERROR(IF(OR(B58="",E58="",B49=0),"",E58*B58/(B49/12)),"") | H58: ea
A59: Facet 8 | B59: =IFERROR(IF(Takeoff!B45="","",Takeoff!B45),"") | C59: =IFERROR(IF(Takeoff!G45="","",Takeoff!G45-N(Takeoff!D45)),"") | D59: =IFERROR(IF(Takeoff!D45="","",Takeoff!D45),"") | E59: =IFERROR(IF(OR(C59="",B46=0),"",MAX(0,ROUNDDOWN((C59-N(B48))/B46,0))),"") | F59: =IFERROR(IF(OR(B59="",E59="",B49=0),"",E59*B59/(B49/12)),"") | H59: ea
A60: TOTAL WALL FASTENING | F60: =IFERROR(IF(COUNT(F52:F59)=0,"",SUM(F52:F59)),"") | G60: =IFERROR(IF(COUNT(G52:G59)=0,"",SUM(G52:G59)),"") | H60: ea
A61: ="Rows = the WALL run (no cap), a row every "&TEXT(B46,"0")&" ft up it, dropping any row that lands inside "&TEXT(B48,"0")&" ft of the top. Fasteners = rows x run ÷ "&TEXT(B49/12,"0.00")&" ft o.c."
A63: 4c · PERIMETER BASE FLASHING — 3" #14 into the WOOD, kept separate from the wall rows above
A64: "Wood deck. Where the base sheet turns up vertical into the wall it takes a 3″ #14 and a seam plate straight into the wood. Going vertical into the wall is what lets a 3″ do the job instead of a 7, 8, 9 or 10 — and it does not leak. On concrete tilt-wall this is not available. This LF is HAND-COUNTED on the takeoff; the wall rows above are derived from wall squares, so the two stay on separate lines."
A65: Item | B65: Driver | C65: Unit | D65: On center (in) | E65: What it means | F65: RAW | G65: Qty | H65: Pkg
A66: Base flashing fastener 3" #14 | B66: =IFERROR(IF(N(Takeoff!B21)>0,Takeoff!B21,Takeoff!I46),"") | C66: LF | D66: =IFERROR(Takeoff!B16,"") | E66: from the SETUP block at the top of the Takeoff page | F66: =IFERROR(IF(OR(B66="",D66="",D66=0),"",B66/(D66/12)),"") | G66: =IFERROR(IF(F66="","",ROUNDUP(F66,0)),"") | H66: ea
A67: Base flashing seam plates | B67: =IFERROR(G66,"") | C67: ea | E67: one plate per fastener | F67: =IFERROR(B67,"") | G67: =IFERROR(IF(F67="","",ROUNDUP(F67,0)),"") | H67: ea
A68: ="Base flashing "&TEXT(N(Takeoff!B21),"#,##0")&" LF at "&TEXT(D66,"0")&"″ o.c. = "&TEXT(N(G66),"#,##0")&" fasteners and the same in plates. Separate line, separate count — it never gets folded into the wall numbers."
A70: 4d · SEAM PLATES & FASTENERS — one fastener per plate
A71: "A roll is 100 ft long no matter how wide it is. Plates run down the seam at the field spacing, so at 12in o.c. every roll takes 100 plates. Count ALL the field rolls — the 10 footers and the 5 footers — then add the details. Every seam plate here is the same plate, so they are bought as one number. The screws are not: the field takes a 5in #15, the walls and base flashing take a 3in #14. Flat metal is NOT in this list — the screws that hold coping, gravel stop and counter flashing are already in the metal price."
A72: Field seam spacing | B72: 12 | C72: in o.c. | E72: THE WIND-UPLIFT LEVER. 12in o.c. = 100 plates per roll, because a roll is 100 ft long. 6in doubles every plate in the field.
A73: Where seam plates go | B73: Count | C73: Unit | D73: Plates each | E73: Which screw | F73: Plates
A74: Field membrane rolls (10 ft + 5 ft) | B74: =IFERROR(N(G28)+N(G29),"") | C74: roll | D74: =IFERROR(IF(N(B72)=0,"",100/(B72/12)),"") | E74: 5″ #15 | F74: =IFERROR(IF(OR(B74="",D74=""),0,B74*D74),"") | I74: =IFERROR(TEXT(N(G28),"0")&" rolls of 10 ft + "&TEXT(N(G29),"0")&" rolls of 5 ft = "&TEXT(N(B74),"0")&" rolls, every one of them 100 ft long. A plate every "&TEXT(N(B72),"0")&" in along the seam = "&TEXT(N(D74),"0")&" plates a roll.","")
A75: Curb flashing | B75: =IFERROR(Takeoff!B26,"") | C75: LF | D75: 1 | E75: 5″ #15 | F75: =IFERROR(IF(OR(B75="",D75=""),0,B75*D75),"")
A76: Pipe boots | B76: =IFERROR(Takeoff!B28,"") | C76: ea | D76: 4 | E76: 5″ #15 | F76: =IFERROR(IF(OR(B76="",D76=""),0,B76*D76),"")
A77: Pitch pans | B77: =IFERROR(Takeoff!B27,"") | C77: ea | D77: 4 | E77: 5″ #15 | F77: =IFERROR(IF(OR(B77="",D77=""),0,B77*D77),"")
A78: Wall fastener rows | B78: =IFERROR(F60,"") | C78: ea | D78: 1 | E78: 3″ #14 | F78: =IFERROR(IF(OR(B78="",D78=""),0,B78*D78),"")
A79: Base flashing | B79: =IFERROR(G66,"") | C79: ea | D79: 1 | E79: 3″ #14 | F79: =IFERROR(IF(OR(B79="",D79=""),0,B79*D79),"")
A80: field plates x 1.1 | C80: plate | F80: =IFERROR(SUM(F74:F77)*1.1,"")
A81: wall plates x 1.1 | C81: plate | F81: =IFERROR(SUM(F78:F79)*1.1,"")
A82: SEAM PLATES | C82: plate | D82: 1.1 | E82: 1000 | F82: =IFERROR(N(F80)+N(F81),"") | G82: =IFERROR(IF(OR(F82="",N(E82)=0),"",ROUNDUP(F82/E82,0)),"") | H82: box
A83: ="All of it added up, then x "&TEXT(D82,"0.0")&" = "&TEXT(N(F82),"#,##0")&" seam plates — one number, one buy. Coping only counts where the wall is part of the roof."
A86: Fasteners — one per plate | B86: Screw | C86: Unit | E86: Per box | F86: Screws | G86: Boxes | H86: Pkg
A87: Insulation fasteners | B87: =IFERROR("#"&TEXT(N(B36),"0")&" x "&TEXT(N(B35),"0")&"in","") | C87: screw | E87: 1000 | F87: =IFERROR(N(F41),"") | G87: =IFERROR(IF(OR(F87="",N(E87)=0),"",ROUNDUP(F87/E87,0)),"") | H87: box
A88: Seam fasteners — 5" | B88: =IFERROR("#"&TEXT(N(B37),"0")&" x 5in","") | C88: screw | E88: 500 | F88: =IFERROR(MAX(0,IF(ISNUMBER(SEARCH("WOOD",UPPER(Takeoff!L38))),N(F80),N(F82))-N(F89)-N(F90)),"") | G88: =IFERROR(IF(OR(F88="",N(E88)=0),"",ROUNDUP(F88/E88,0)),"") | H88: box | I88: the screws in the 7 in. and 8 in. boxes are SUBTRACTED here - same job, just longer where the crickets build up.
A89: Seam fasteners — 7" | B89: #15 x 7in | C89: screw | E89: 500 | F89: =IFERROR(N(G89)*N(E89),"") | H89: box | I89: for the crickets — one box
A90: Seam fasteners — 8" | B90: #15 x 8in | C90: screw | E90: 500 | F90: =IFERROR(N(G90)*N(E90),"") | H90: box | I90: for the crickets — one box
A91: TOTAL SCREWS ON THIS ROOF | F91: =IFERROR(N(F87)+N(F88)+N(F89)+N(F90),"") | G91: =IFERROR(N(G87)+N(G88)+N(G89)+N(G90),"") | H91: box
A92: ="Seam plates call for "&TEXT(IF(ISNUMBER(SEARCH("WOOD",UPPER(Takeoff!L38))),N(F80),N(F82)),"#,##0")&" screws. Take out "&TEXT(N(F89)+N(F90),"#,##0")&" that go long ("&TEXT(N(G89),"0")&" box at 7in + "&TEXT(N(G90),"0")&" box at 8in) and "&TEXT(N(F88),"#,##0")&" are left at 5in = "&TEXT(N(G88),"0")&" box. "&TEXT(N(G88)+N(G89)+N(G90),"0")&" boxes of seam screw either way - the long ones come OUT of the 5 in. count, never on top of it."
A93: 5 · ADHESIVE & CONSUMABLES
A94: Curb flashing height | B94: 2 | C94: ft | E94: turns the curb LF into square feet for the adhesive. Lives here, not on the Takeoff page.
A95: "THE DIVISOR IS NOT THE SAME ON A TEAR-OFF AS IT IS ON NEW CONSTRUCTION. A tear-off has overnight tie-ins all day long, so every one of these gets used harder: more cut edges to seal, more cleaner, more rags. The job type comes off the EXISTING page and the divisors switch themselves. Recover is not set yet."
A96: Item | B96: Driver | C96: Unit | D96: Factor | E96: What the factor means | F96: RAW | G96: Qty | H96: Pkg
A97: Bonding adhesive | B97: =IFERROR(N(G8)+N(Takeoff!B26)*N(B94)/100,"") | C97: wall sq + curb sq | D97: 3 | E97: wall squares plus the curb, per pail | F97: =IFERROR(IF(OR(B97="",D97="",D97=0),"",B97/D97),"") | G97: =IFERROR(IF(F97="","",ROUNDUP(F97,0)),"") | H97: pail
A98: Unsupported / flashing | B98: =IFERROR(G9,"") | C98: total sq | D98: 150 | E98: one roll every 150 squares | F98: =IFERROR(IF(OR(B98="",D98="",D98=0),"",B98/D98),"") | G98: =IFERROR(IF(F98="","",IF(MOD(F98,1)<=0.25,ROUNDDOWN(F98,0),ROUNDUP(F98,0))),"") | H98: roll
A99: TPO cleaner 5g | B99: =IFERROR(G9,"") | C99: total sq | D99: =IF(ISNUMBER(SEARCH("TEAR",UPPER(Existing!B6))),30,75) | E99: =IF(ISNUMBER(SEARCH("TEAR",UPPER(Existing!B6))),"TEAR-OFF: one 5-gallon can every 30 squares. All the tie-ins mean a lot more cleaning.","NEW CONSTRUCTION: one 5-gallon can every 75 squares.") | F99: =IFERROR(IF(OR(B99="",D99="",D99=0),"",B99/D99),"") | G99: =IFERROR(IF(F99="","",IF(MOD(F99,1)<=0.25,ROUNDDOWN(F99,0),ROUNDUP(F99,0))),"") | H99: can
A100: TPO T-joints | B100: =IFERROR(G9,"") | C100: total sq | D100: 100 | E100: one box of 100 every 100 squares | F100: =IFERROR(IF(OR(B100="",D100="",D100=0),"",B100/D100),"") | G100: =IFERROR(IF(F100="","",IF(MOD(F100,1)<=0.25,ROUNDDOWN(F100,0),ROUNDUP(F100,0))),"") | H100: box
A101: TPO cut-edge sealant | B101: =IFERROR(G9,"") | C101: total sq | D101: =IF(ISNUMBER(SEARCH("TEAR",UPPER(Existing!B6))),15,30) | E101: =IF(ISNUMBER(SEARCH("TEAR",UPPER(Existing!B6))),"TEAR-OFF: one tube every 15 squares. Every place you cut a roll needs it, and a tear-off has far more overnight tie-ins than normal.","NEW CONSTRUCTION: one tube every 30 squares.") | F101: =IFERROR(IF(OR(B101="",D101="",D101=0),"",B101/D101),"") | G101: =IFERROR(IF(F101="","",IF(MOD(F101,1)<=0.25,ROUNDDOWN(F101,0),ROUNDUP(F101,0))),"") | H101: tube
A102: TPO LVOC all-purpose | B102: =IFERROR(G9,"") | C102: total sq | D102: =IF(ISNUMBER(SEARCH("TEAR",UPPER(Existing!B6))),10,20) | E102: =IF(ISNUMBER(SEARCH("TEAR",UPPER(Existing!B6))),"TEAR-OFF: one can every 10 squares.","NEW CONSTRUCTION: one can every 20 squares.") | F102: =IFERROR(IF(OR(B102="",D102="",D102=0),"",B102/D102),"") | G102: =IFERROR(IF(F102="","",ROUNDUP(F102,0)),"") | H102: can
A103: Water block | B103: =IFERROR(N(G102)+N(Takeoff!B34),"") | C103: cans + drains | D103: 1 | E103: ="one for every LVOC can, plus one for every drain. The drains get added no matter what — tear-off or new construction." | F103: =IFERROR(IF(OR(B103="",D103="",D103=0),"",B103/D103),"") | G103: =IFERROR(IF(F103="","",ROUNDUP(F103,0)),"") | H103: tube
A104: Backer rod | B104: =IFERROR(N(Takeoff!B31),"") | C104: roof hatch | D104: 1 | E104: one bag per roof hatch | F104: =IFERROR(IF(OR(B104="",D104="",D104=0),"",B104/D104),"") | G104: =IFERROR(IF(F104="","",ROUNDUP(F104,0)),"") | H104: bag
A105: Rags | B105: =IFERROR(G9,"") | C105: total sq | D105: =IF(ISNUMBER(SEARCH("TEAR",UPPER(Existing!B6))),15,30) | E105: =IF(ISNUMBER(SEARCH("TEAR",UPPER(Existing!B6))),"TEAR-OFF: one box every 15 squares.","NEW CONSTRUCTION: one box every 30 squares.") | F105: =IFERROR(IF(OR(B105="",D105="",D105=0),"",B105/D105),"") | G105: =IFERROR(IF(F105="","",ROUNDUP(F105,0)),"") | H105: box
A106: Hose clamps | B106: =IFERROR(G9,"") | C106: total sq | D106: 25 | E106: ="A QUARTER ROLL EVERY 25 SQUARES. Under 20 sq = 1/4 roll · 50 sq = 1/2 · 75 sq = 3/4 · 100 sq = 1 roll, and up in quarters from there." | F106: =IFERROR(IF(OR(B106="",D106="",D106=0),"",B106/D106),"") | G106: =IFERROR(IF(F106="","",MAX(0.25,ROUNDUP(F106,0)/4)),"") | H106: roll
A107: Retro drains | B107: =IFERROR(IF(ISNUMBER(SEARCH("TEAR",UPPER(Existing!B6))),N(Takeoff!B34),0),"") | C107: drains | D107: 1 | E107: =IF(ISNUMBER(SEARCH("TEAR",UPPER(Existing!B6))),"one retro drain per existing drain — tear-off only","NEW CONSTRUCTION: a retro drain is never an option here") | F107: =IFERROR(IF(OR(B107="",D107="",D107=0),"",B107/D107),"") | G107: =IFERROR(IF(F107="","",ROUNDUP(F107,0)),"") | H107: ea
A108: Rollers | B108: =IFERROR(N(G8)+N(Takeoff!B26)*N(B94)/100,"") | C108: adhesive sq | D108: 3 | E108: one roller every 3 squares of adhesive | F108: =IFERROR(IF(OR(B108="",D108="",D108=0),"",B108/D108),"") | G108: =IFERROR(IF(F108="","",ROUNDUP(F108,0)),"") | H108: ea
A109: Cages | B109: =IFERROR(N(G8)+N(Takeoff!B26)*N(B94)/100,"") | C109: adhesive sq | D109: 3 | E109: one cage every 3 squares of adhesive | F109: =IFERROR(IF(OR(B109="",D109="",D109=0),"",B109/D109),"") | G109: =IFERROR(IF(F109="","",ROUNDUP(F109,0)),"") | H109: ea
A110: Sticks | B110: =IFERROR(G9,"") | C110: total sq | D110: 50 | E110: one stick every 50 squares | F110: =IFERROR(IF(OR(B110="",D110="",D110=0),"",B110/D110),"") | G110: =IFERROR(IF(F110="","",ROUNDUP(F110,0)),"") | H110: ea
A111: Primer | B111: =IFERROR(IF(N(Takeoff!B66)>0,N(Takeoff!B66),N(Takeoff!B76)),"") | C111: gravel stop LF | D111: 300 | E111: one 3-gallon can every 300 ft of gravel stop | F111: =IFERROR(IF(OR(B111="",D111="",D111=0),"",B111/D111),"") | G111: =IFERROR(IF(F111="","",IF(MOD(F111,1)<=0.25,ROUNDDOWN(F111,0),ROUNDUP(F111,0))),"") | H111: can
A112: Brushes | B112: =IFERROR(IF(N(Takeoff!B66)>0,N(Takeoff!B66),N(Takeoff!B76)),"") | C112: gravel stop LF | D112: 50 | E112: one brush every 50 ft of gravel stop | F112: =IFERROR(IF(OR(B112="",D112="",D112=0),"",B112/D112),"") | G112: =IFERROR(IF(F112="","",ROUNDUP(F112,0)),"") | H112: ea
A113: TPO cover tape | B113: =IFERROR(IF(N(Takeoff!B66)>0,N(Takeoff!B66),N(Takeoff!B76)),"") | C113: gravel stop LF | D113: 100 | E113: 100 ft roll — gravel stop LF ÷ 100 | F113: =IFERROR(IF(OR(B113="",D113="",D113=0),"",B113/D113),"") | G113: =IFERROR(IF(F113="","",ROUNDUP(F113,0)),"") | H113: roll
...

Sheet Lists
A1: SETUP LISTS — every dropdown on the Takeoff page reads its choices from the column under it
A2: HOW TO ADD A CHOICE THAT STICKS FOREVER: type it in the first empty cell under the heading. It is in that dropdown from then on, on this job and on every new bid started from this template. Nothing else to do. To retire a choice, delete the cell.
S3: Wood deck material | T3: Steel deck profile
A4: System | B4: Deck type | C4: Insulation thickness (in) | D4: Cover board thickness (in) | E4: Membrane thickness (mil) | F4: Field membrane sheet width (ft) | G4: ISO plates per board (ea) | H4: Wall fastener spacing (in) | I4: Base flashing spacing (in) | J4: Yes / No | K4: Field seam spacing (in) | L4: Construction type | M4: Decking | N4: Roof layer type | O4: How it is attached | P4: Insulation? (what board) | Q4: Gravel? | R4: Wall substrate
A5: ISO MA / TPO MA | B5: METAL | E5: 60 | F5: 5 | G5: 5 | H5: 6 | I5: 6 | J5: Y | K5: 6 | L5: Tear off | M5: Lightweight concrete over steel | N5: Modified bitumen | O5: Mechanically attached | P5: Recover board | Q5: Y | R5: Concrete | S5: OSB | T5: R panel
B6: WOOD | F6: 10 | H6: 12 | I6: 12 | J6: N | K6: 12 | L6: Recover | M6: Steel | N6: BUR | O6: Fully adhered | P6: ISO | Q6: N | R6: Wood | S6: Planks | T6: B deck
B7: CONCRETE | L7: Retrofit | M7: Wood | N7: TPO | O7: Mopped | P7: N/A | Q7: n/a | R7: Metal | S7: Plywood
B8: LWIC w/ metal pan | M8: Structural concrete | N8: PVC | O8: Torched
N9: Recover board + TPO | O9: Rhinobond
N10: Recover board + PVC | O10: Foamed
N11: N/A | O11: Loose laid / ballasted
O12: N/A
